Workbook

Sheet 01_Society_Master
A1: Sr. No. | B1: Field | C1: Value | D1: Line 1 | E1: Line 2 | F1: Line 3 | G1: Line 4 | H1: Line 5 | I1: Line 6
A2: 1 | B2: Society Name
A3: 2 | B3: Society Registration No.
A4: 3 | B4: Society Registration Date
A5: 4 | B5: Hedder Address
A6: 5 | B6: Society Address
A7: 6 | B7: Society Email Id
A8: 7 | B8: Society Telephone or Mobile No.
A9: 8 | B9: Total Unit
B10: A) No. of Flat or Room
B11: B) No. Shop
B12: C) No. Office
B13: D) No. Galas
A14: 9 | B14: No. of Print Blank (EXTRA SR. No.)
A15: 10 | B15: Total Unit

Sheet 02_Common_Member_Master
A1: Sr. No. | B1: Membership No. | C1: Share Certificate No. | D1: No. of Shares | E1: Value of One Share | F1: Value of Shares | G1: Share Certificate Range | I1: Members Name Full | O1: Address Permanent | Q1: Address Residential / Care of
G2: From | H2: To | I2: 1 | J2: 2 | K2: 3 | L2: 4 | M2: 5 | N2: 6 | O2: Flat/Room/Shop/Office/Gala No. | P2: Wing No. | Q2: New Address / As Above
A3: 1 | B3: 1 | C3: 1 | D3: 10 (Ten) | E3: 50/- Each | F3: 500/- | G3: 1 | H3: 10 | I3: Nafisha Khatoon Sharif Ahmed Khan | O3: 1/01 | Q3: C.S. No. 364(Pt.), 365(Pt.),366(Pt.), Division Dadar, Naigaon, R. A. Kidwai Marg, Wadala, Mumbai - 400031.
A4: 2 | B4: 2 | C4: 2 | D4: 10 (Ten) | E4: 50/- Each | F4: 500/- | G4: =H3+1 -> 11 | H4: =G4+9 -> 20 | I4: Azhar Husain Mazhar Husain Khan | O4: 1/03 | Q4: C.S. No. 364(Pt.), 365(Pt.),366(Pt.), Division Dadar, Naigaon, R. A. Kidwai Marg, Wadala, Mumbai - 400031.
A5: 3 | B5: 3 | C5: 3 | D5: 10 (Ten) | E5: 50/- Each | F5: 500/- | G5: =H4+1 -> 21 | H5: =G5+9 -> 30 | I5: Abdul Malik Azhar Husain Khan | O5: 1/04 | Q5: C.S. No. 364(Pt.), 365(Pt.),366(Pt.), Division Dadar, Naigaon, R. A. Kidwai Marg, Wadala, Mumbai - 400031.
A6: 4 | B6: 4 | C6: 4 | D6: 10 (Ten) | E6: 50/- Each | F6: 500/- | G6: =H5+1 -> 31 | H6: =G6+9 -> 40 | I6: Abdul Wadood Abdul Mannan Sayyed | O6: 1/09 | Q6: C.S. No. 364(Pt.), 365(Pt.),366(Pt.), Division Dadar, Naigaon, R. A. Kidwai Marg, Wadala, Mumbai - 400031.
A7: 5 | B7: 5 | C7: 5 | D7: 10 (Ten) | E7: 50/- Each | F7: 500/- | G7: =H6+1 -> 41 | H7: =G7+9 -> 50 | I7: Abdulhai Abdul Mannan Sayyed | O7: 1/11 | Q7: C.S. No. 364(Pt.), 365(Pt.),366(Pt.), Division Dadar, Naigaon, R. A. Kidwai Marg, Wadala, Mumbai - 400031.
A8: 6 | B8: 6 | C8: 6 | D8: 10 (Ten) | E8: 50/- Each | F8: 500/- | G8: =H7+1 -> 51 | H8: =G8+9 -> 60 | I8: Shakeel Ahmed Nazir Ahmed Khan | O8: 1/13 | Q8: C.S. No. 364(Pt.), 365(Pt.),366(Pt.), Division Dadar, Naigaon, R. A. Kidwai Marg, Wadala, Mumbai - 400031.
A9: 7 | B9: 7 | C9: 7 | D9: 10 (Ten) | E9: 50/- Each | F9: 500/- | G9: =H8+1 -> 61 | H9: =G9+9 -> 70 | I9: Mohammed Nawaz Ramzan Ali Shaikh | O9: 1/14 | Q9: C.S. No. 364(Pt.), 365(Pt.),366(Pt.), Division Dadar, Naigaon, R. A. Kidwai Marg, Wadala, Mumbai - 400031.
A10: 8 | B10: 8 | C10: 8 | D10: 10 (Ten) | E10: 50/- Each | F10: 500/- | G10: =H9+1 -> 71 | H10: =G10+9 -> 80 | I10: Gulam Husain Kutbullah Khan | O10: 1/15 | Q10: C.S. No. 364(Pt.), 365(Pt.),366(Pt.), Division Dadar, Naigaon, R. A. Kidwai Marg, Wadala, Mumbai - 400031.
A11: 9 | B11: 9 | C11: 9 | D11: 10 (Ten) | E11: 50/- Each | F11: 500/- | G11: =H10+1 -> 81 | H11: =G11+9 -> 90 | I11: Sajid Azhar Husain Khan | O11: 1/16 | Q11: C.S. No. 364(Pt.), 365(Pt.),366(Pt.), Division Dadar, Naigaon, R. A. Kidwai Marg, Wadala, Mumbai - 400031.
A12: 10 | B12: 10 | C12: 10 | D12: 10 (Ten) | E12: 50/- Each | F12: 500/- | G12: =H11+1 -> 91 | H12: =G12+9 -> 100 | I12: Shakilabanoo Mohamed Iqbal Khan | O12: 2/01 | Q12: C.S. No. 364(Pt.), 365(Pt.),366(Pt.), Division Dadar, Naigaon, R. A. Kidwai Marg, Wadala, Mumbai - 400031.
A13: 11 | B13: 11 | C13: 11 | D13: 10 (Ten) | E13: 50/- Each | F13: 500/- | G13: =H12+1 -> 101 | H13: =G13+9 -> 110 | I13: Mohd Hashim Anwarul Haque Khan | O13: 2/02 | Q13: C.S. No. 364(Pt.), 365(Pt.),366(Pt.), Division Dadar, Naigaon, R. A. Kidwai Marg, Wadala, Mumbai - 400031.
A14: 12 | B14: 12 | C14: 12 | D14: 10 (Ten) | E14: 50/- Each | F14: 500/- | G14: =H13+1 -> 111 | H14: =G14+9 -> 120 | I14: Mohammed Shoyab Mohammed Faique Farooque | O14: 2/04 | Q14: C.S. No. 364(Pt.), 365(Pt.),366(Pt.), Division Dadar, Naigaon, R. A. Kidwai Marg, Wadala, Mumbai - 400031.
A15: 13 | B15: 13 | C15: 13 | D15: 10 (Ten) | E15: 50/- Each | F15: 500/- | G15: =H14+1 -> 121 | H15: =G15+9 -> 130 | I15: Ruksana Rashid Ahmed Khan | O15: 2/05 | Q15: C.S. No. 364(Pt.), 365(Pt.),366(Pt.), Division Dadar, Naigaon, R. A. Kidwai Marg, Wadala, Mumbai - 400031.
... A43: 41 | B43: 41 | C43: 41 | D43: 10 (Ten) | E43: 50/- Each | F43: 500/- | G43: =H42+1 -> 401 | H43: =G43+9 -> 410 | I43: Mehboob Azizuddin Khan | O43: 5/03 | Q43: C.S. No. 364(Pt.), 365(Pt.),366(Pt.), Division Dadar, Naigaon, R. A. Kidwai Marg, Wadala, Mumbai - 400031.
A44: 42 | B44: 42 | C44: 42 | D44: 10 (Ten) | E44: 50/- Each | F44: 500/- | G44: =H43+1 -> 411 | H44: =G44+9 -> 420 | I44: Imtiyaz Ali Khan, Afzal Ali Moharram Ali Khan, | J44: Miraz Ali Moharram Ali khan, Abdul Rehman Moharram Ali Khan | K44: Imran Ali Moharram Ali Khan | O44: 5/04 | Q44: C.S. No. 364(Pt.), 365(Pt.),366(Pt.), Division Dadar, Naigaon, R. A. Kidwai Marg, Wadala, Mumbai - 400031.
A45: 43 | B45: 43 | C45: 43 | D45: 10 (Ten) | E45: 50/- Each | F45: 500/- | G45: =H44+1 -> 421 | H45: =G45+9 -> 430 | I45: Sayed Haroon Ali | O45: 5/07 | Q45: C.S. No. 364(Pt.), 365(Pt.),366(Pt.), Division Dadar, Naigaon, R. A. Kidwai Marg, Wadala, Mumbai - 400031.
A46: 44 | B46: 44 | C46: 44 | D46: 10 (Ten) | E46: 50/- Each | F46: 500/- | G46: =H45+1 -> 431 | H46: =G46+9 -> 440 | I46: Ural Pereira & Nirmala Pereira | O46: 5/09 | Q46: C.S. No. 364(Pt.), 365(Pt.),366(Pt.), Division Dadar, Naigaon, R. A. Kidwai Marg, Wadala, Mumbai - 400031.
A47: 45 | B47: 45 | C47: 45 | D47: 10 (Ten) | E47: 50/- Each | F47: 500/- | G47: =H46+1 -> 441 | H47: =G47+9 -> 450 | I47: Alwyn Joseph Stanley Texeira | O47: 5/10 | Q47: C.S. No. 364(Pt.), 365(Pt.),366(Pt.), Division Dadar, Naigaon, R. A. Kidwai Marg, Wadala, Mumbai - 400031.
A48: 46 | B48: 46 | C48: 46 | D48: 10 (Ten) | E48: 50/- Each | F48: 500/- | G48: =H47+1 -> 451 | H48: =G48+9 -> 460 | I48: Riyaz Ahmed Siraj Ahmed Ansari | O48: 5/11 | Q48: C.S. No. 364(Pt.), 365(Pt.),366(Pt.), Division Dadar, Naigaon, R. A. Kidwai Marg, Wadala, Mumbai - 400031.
A49: 47 | B49: 47 | C49: 47 | D49: 10 (Ten) | E49: 50/- Each | F49: 500/- | G49: =H48+1 -> 461 | H49: =G49+9 -> 470 | I49: Adrian Stephen Gomes | O49: 5/14 | Q49: C.S. No. 364(Pt.), 365(Pt.),366(Pt.), Division Dadar, Naigaon, R. A. Kidwai Marg, Wadala, Mumbai - 400031.
A50: 48 | B50: 48 | C50: 48 | D50: 10 (Ten) | E50: 50/- Each | F50: 500/- | G50: =H49+1 -> 471 | H50: =G50+9 -> 480 | I50: Ayeshabi Abdul Rashid Shaikh | O50: 5/16 | Q50: C.S. No. 364(Pt.), 365(Pt.),366(Pt.), Division Dadar, Naigaon, R. A. Kidwai Marg, Wadala, Mumbai - 400031.
A51: 49 | B51: 49 | C51: 49 | D51: 10 (Ten) | E51: 50/- Each | F51: 500/- | G51: =H50+1 -> 481 | H51: =G51+9 -> 490 | I51: Zaibunnissa Naeem Chippa | O51: 6/03 | Q51: C.S. No. 364(Pt.), 365(Pt.),366(Pt.), Division Dadar, Naigaon, R. A. Kidwai Marg, Wadala, Mumbai - 400031.
A52: 50 | B52: 50 | C52: 50 | D52: 10 (Ten) | E52: 50/- Each | F52: 500/- | G52: =H51+1 -> 491 | H52: =G52+9 -> 500 | I52: Naseem Bano Mohammed Rayees Chippa | O52: 6/04 | Q52: C.S. No. 364(Pt.), 365(Pt.),366(Pt.), Division Dadar, Naigaon, R. A. Kidwai Marg, Wadala, Mumbai - 400031.
A53: 51 | B53: 51 | C53: 51 | D53: 10 (Ten) | E53: 50/- Each | F53: 500/- | G53: =H52+1 -> 501 | H53: =G53+9 -> 510 | I53: Fatma Yaqub Shaikh | O53: 6/06 | Q53: C.S. No. 364(Pt.), 365(Pt.),366(Pt.), Division Dadar, Naigaon, R. A. Kidwai Marg, Wadala, Mumbai - 400031.
A54: 52 | B54: 52 | C54: 52 | D54: 10 (Ten) | E54: 50/- Each | F54: 500/- | G54: =H53+1 -> 511 | H54: =G54+9 -> 520 | I54: Rabiya Begum Ishaque Hussain Khan (Late) | O54: 6/07 | Q54: C.S. No. 364(Pt.), 365(Pt.),366(Pt.), Division Dadar, Naigaon, R. A. Kidwai Marg, Wadala, Mumbai - 400031.
A55: 53 | B55: 53 | C55: 53 | D55: 10 (Ten) | E55: 50/- Each | F55: 500/- | G55: =H54+1 -> 521 | H55: =G55+9 -> 530 | I55: Ishaque Hussain Imdad Hussain Khan | O55: 6/08 | Q55: C.S. No. 364(Pt.), 365(Pt.),366(Pt.), Division Dadar, Naigaon, R. A. Kidwai Marg, Wadala, Mumbai - 400031.
A56: 54 | B56: 54 | C56: 54 | D56: 10 (Ten) | E56: 50/- Each | F56: 500/- | G56: =H55+1 -> 531 | H56: =G56+9 -> 540 | I56: Mohammed Jakir Sabir Ali Sayyed | O56: 6/09 | Q56: C.S. No. 364(Pt.), 365(Pt.),366(Pt.), Division Dadar, Naigaon, R. A. Kidwai Marg, Wadala, Mumbai - 400031.
... A65: 63 | B65: 63 | C65: 63 | D65: 10 (Ten) | E65: 50/- Each | F65: 500/- | G65: =H64+1 -> 621 | H65: =G65+9 -> 630 | I65: Jaitunnisa Sirajuddin Khan | O65: 7/04 | Q65: C.S. No. 364(Pt.), 365(Pt.),366(Pt.), Division Dadar, Naigaon, R. A. Kidwai Marg, Wadala, Mumbai - 400031.
A66: 64 | B66: 64 | C66: 64 | D66: 10 (Ten) | E66: 50/- Each | F66: 500/- | G66: =H65+1 -> 631 | H66: =G66+9 -> 640 | I66: Sandip Shantaram Kargutkar | J66: Pradeep Shantaram Kargutkar | O66: 7/06 | Q66: C.S. No. 364(Pt.), 365(Pt.),366(Pt.), Division Dadar, Naigaon, R. A. Kidwai Marg, Wadala, Mumbai - 400031.
A67: 65 | B67: 65 | C67: 65 | D67: 10 (Ten) | E67: 50/- Each | F67: 500/- | G67: =H66+1 -> 641 | H67: =G67+9 -> 650 | I67: Noor Mohammed Habibullah Siddiqui | O67: 7/12 | Q67: C.S. No. 364(Pt.), 365(Pt.),366(Pt.), Division Dadar, Naigaon, R. A. Kidwai Marg, Wadala, Mumbai - 400031.
A68: 66 | B68: 66 | C68: 66 | D68: 10 (Ten) | E68: 50/- Each | F68: 500/- | G68: =H67+1 -> 651 | H68: =G68+9 -> 660 | I68: Abdussalam Kassim Miya Pawaskar | O68: 7/13 | Q68: C.S. No. 364(Pt.), 365(Pt.),366(Pt.), Division Dadar, Naigaon, R. A. Kidwai Marg, Wadala, Mumbai - 400031.
A69: 67 | B69: 67 | C69: 67 | D69: 10 (Ten) | E69: 50/- Each | F69: 500/- | G69: =H68+1 -> 661 | H69: =G69+9 -> 670 | I69: Ganesh Anant Patil | J69: Dinesh Anant Patil | K69: Bharat Anant Patil | O69: 7/14 | Q69: C.S. No. 364(Pt.), 365(Pt.),366(Pt.), Division Dadar, Naigaon, R. A. Kidwai Marg, Wadala, Mumbai - 400031.
A70: 68 | B70: 68 | C70: 68 | D70: 10 (Ten) | E70: 50/- Each | F70: 500/- | G70: =H69+1 -> 671 | H70: =G70+9 -> 680 | I70: Rashid Nawaz Rafiq Ahmed Shaikh | O70: 7/15 | Q70: C.S. No. 364(Pt.), 365(Pt.),366(Pt.), Division Dadar, Naigaon, R. A. Kidwai Marg, Wadala, Mumbai - 400031.
A71: 69 | B71: 69 | C71: 69 | D71: 10 (Ten) | E71: 50/- Each | F71: 500/- | G71: =H70+1 -> 681 | H71: =G71+9 -> 690 | I71: Ashikali Abdulla Khan | O71: 7/16 | Q71: C.S. No. 364(Pt.), 365(Pt.),366(Pt.), Division Dadar, Naigaon, R. A. Kidwai Marg, Wadala, Mumbai - 400031.
A72: 70 | B72: 70 | C72: 70 | D72: 10 (Ten) | E72: 50/- Each | F72: 500/- | G72: =H71+1 -> 691 | H72: =G72+9 -> 700 | I72: Dayaram Gangaprasad Pal | O72: 8/01 | Q72: C.S. No. 364(Pt.), 365(Pt.),366(Pt.), Division Dadar, Naigaon, R. A. Kidwai Marg, Wadala, Mumbai - 400031.
A73: 71 | B73: 71 | C73: 71 | D73: 10 (Ten) | E73: 50/- Each | F73: 500/- | G73: =H72+1 -> 701 | H73: =G73+9 -> 710 | I73: Abdul Hamid Khan | O73: 8/04 | Q73: C.S. No. 364(Pt.), 365(Pt.),366(Pt.), Division Dadar, Naigaon, R. A. Kidwai Marg, Wadala, Mumbai - 400031.
A74: 72 | B74: 72 | C74: 72 | D74: 10 (Ten) | E74: 50/- Each | F74: 500/- | G74: =H73+1 -> 711 | H74: =G74+9 -> 720 | I74: Maimuna khatun Jameel Ahmed Khan | O74: 8/05 | Q74: C.S. No. 364(Pt.), 365(Pt.),366(Pt.), Division Dadar, Naigaon, R. A. Kidwai Marg, Wadala, Mumbai - 400031.
A75: 73 | B75: 73 | C75: 73 | D75: 10 (Ten) | E75: 50/- Each | F75: 500/- | G75: =H74+1 -> 721 | H75: =G75+9 -> 730 | I75: Gulshan Bano Abdul Hafeez Khan | O75: 8/06 | Q75: C.S. No. 364(Pt.), 365(Pt.),366(Pt.), Division Dadar, Naigaon, R. A. Kidwai Marg, Wadala, Mumbai - 400031.
A76: 74 | B76: 74 | C76: 74 | D76: 10 (Ten) | E76: 50/- Each | F76: 500/- | G76: =H75+1 -> 731 | H76: =G76+9 -> 740 | I76: Amjad Ali Bechu Khan | O76: 8/07 | Q76: C.S. No. 364(Pt.), 365(Pt.),366(Pt.), Division Dadar, Naigaon, R. A. Kidwai Marg, Wadala, Mumbai - 400031.
A77: 75 | B77: 75 | C77: 75 | D77: 10 (Ten) | E77: 50/- Each | F77: 500/- | G77: =H76+1 -> 741 | H77: =G77+9 -> 750 | I77: Abdul Rashid Abdul Gani Shah | O77: 8/08 | Q77: C.S. No. 364(Pt.), 365(Pt.),366(Pt.), Division Dadar, Naigaon, R. A. Kidwai Marg, Wadala, Mumbai - 400031.
A78: 76 | B78: 76 | C78: 76 | D78: 10 (Ten) | E78: 50/- Each | F78: 500/- | G78: =H77+1 -> 751 | H78: =G78+9 -> 760 | I78: Raisa Khatoon Abdul Mabood Sayyed | O78: 8/11 | Q78: C.S. No. 364(Pt.), 365(Pt.),366(Pt.), Division Dadar, Naigaon, R. A. Kidwai Marg, Wadala, Mumbai - 400031.
A79: 77 | B79: 77 | C79: 77 | D79: 10 (Ten) | E79: 50/- Each | F79: 500/- | G79: =H78+1 -> 761 | H79: =G79+9 -> 770 | I79: Mohammed Yaseen Abdul Rehman Chippa | O79: 8/14 | Q79: C.S. No. 364(Pt.), 365(Pt.),366(Pt.), Division Dadar, Naigaon, R. A. Kidwai Marg, Wadala, Mumbai - 400031.
A80: 78 | B80: 78 | C80: 78 | D80: 10 (Ten) | E80: 50/- Each | F80: 500/- | G80: =H79+1 -> 771 | H80: =G80+9 -> 780 | I80: Sayeed Ahmed Abdul Rehman Chippa | O80: 8/15 | Q80: C.S. No. 364(Pt.), 365(Pt.),366(Pt.), Division Dadar, Naigaon, R. A. Kidwai Marg, Wadala, Mumbai - 400031.
A81: 79 | B81: 79 | C81: 79 | D81: 10 (Ten) | E81: 50/- Each | F81: 500/- | G81: =H80+1 -> 781 | H81: =G81+9 -> 790 | I81: Imamuddin Nooruddin Sayyed | O81: 8/16 | Q81: C.S. No. 364(Pt.), 365(Pt.),366(Pt.), Division Dadar, Naigaon, R. A. Kidwai Marg, Wadala, Mumbai - 400031.
... A88: 86 | B88: 86 | C88: 86 | D88: 10 (Ten) | E88: 50/- Each | F88: 500/- | G88: =H87+1 -> 851 | H88: =G88+9 -> 860 | I88: Abubaker Mohammed Siddique Khatri | O88: 9/09 | Q88: C.S. No. 364(Pt.), 365(Pt.),366(Pt.), Division Dadar, Naigaon, R. A. Kidwai Marg, Wadala, Mumbai - 400031.
A89: 87 | B89: 87 | C89: 87 | D89: 10 (Ten) | E89: 50/- Each | F89: 500/- | G89: =H88+1 -> 861 | H89: =G89+9 -> 870 | I89: Abdul Aleem Abdul Wahab Khan | J89: Abdul salim Abdul Wahab khan | O89: 9/11 | Q89: C.S. No. 364(Pt.), 365(Pt.),366(Pt.), Division Dadar, Naigaon, R. A. Kidwai Marg, Wadala, Mumbai - 400031.
A90: 88 | B90: 88 | C90: 88 | D90: 10 (Ten) | E90: 50/- Each | F90: 500/- | G90: =H89+1 -> 871 | H90: =G90+9 -> 880 | I90: Mazida | O90: 9/12 | Q90: C.S. No. 364(Pt.), 365(Pt.),366(Pt.), Division Dadar, Naigaon, R. A. Kidwai Marg, Wadala, Mumbai - 400031.
A91: 89 | B91: 89 | C91: 89 | D91: 10 (Ten) | E91: 50/- Each | F91: 500/- | G91: =H90+1 -> 881 | H91: =G91+9 -> 890 | I91: Ibrahim Siddique Khatri | O91: 9/13 | Q91: C.S. No. 364(Pt.), 365(Pt.),366(Pt.), Division Dadar, Naigaon, R. A. Kidwai Marg, Wadala, Mumbai - 400031.
A92: 90 | B92: 90 | C92: 90 | D92: 10 (Ten) | E92: 50/- Each | F92: 500/- | G92: =H91+1 -> 891 | H92: =G92+9 -> 900 | I92: Mohammed Arif Siddique Khatri | O92: 9/14 | Q92: C.S. No. 364(Pt.), 365(Pt.),366(Pt.), Division Dadar, Naigaon, R. A. Kidwai Marg, Wadala, Mumbai - 400031.
A93: 91 | B93: 91 | C93: 91 | D93: 10 (Ten) | E93: 50/- Each | F93: 500/- | G93: =H92+1 -> 901 | H93: =G93+9 -> 910 | I93: Sarvari Begam Haider Hussain Sayyed | O93: 10/01 | Q93: C.S. No. 364(Pt.), 365(Pt.),366(Pt.), Division Dadar, Naigaon, R. A. Kidwai Marg, Wadala, Mumbai - 400031.
A94: 92 | B94: 92 | C94: 92 | D94: 10 (Ten) | E94: 50/- Each | F94: 500/- | G94: =H93+1 -> 911 | H94: =G94+9 -> 920 | I94: Ibne Hasan Abdul Gani Malik | O94: 10/02 | Q94: C.S. No. 364(Pt.), 365(Pt.),366(Pt.), Division Dadar, Naigaon, R. A. Kidwai Marg, Wadala, Mumbai - 400031.
A95: 93 | B95: 93 | C95: 93 | D95: 10 (Ten) | E95: 50/- Each | F95: 500/- | G95: =H94+1 -> 921 | H95: =G95+9 -> 930 | I95: Asgar Ali Mohammad Hanif Siddiqui | O95: 10/03 | Q95: C.S. No. 364(Pt.), 365(Pt.),366(Pt.), Division Dadar, Naigaon, R. A. Kidwai Marg, Wadala, Mumbai - 400031.
A96: 94 | B96: 94 | C96: 94 | D96: 10 (Ten) | E96: 50/- Each | F96: 500/- | G96: =H95+1 -> 931 | H96: =G96+9 -> 940 | I96: Taslimunnisa Salahuddin Siddiqui | O96: 10/04 | Q96: C.S. No. 364(Pt.), 365(Pt.),366(Pt.), Division Dadar, Naigaon, R. A. Kidwai Marg, Wadala, Mumbai - 400031.
A97: 95 | B97: 95 | C97: 95 | D97: 10 (Ten) | E97: 50/- Each | F97: 500/- | G97: =H96+1 -> 941 | H97: =G97+9 -> 950 | I97: Mohammed Shamim Mohammed Ismail Sayyed | O97: 10/06 | Q97: C.S. No. 364(Pt.), 365(Pt.),366(Pt.), Division Dadar, Naigaon, R. A. Kidwai Marg, Wadala, Mumbai - 400031.
A98: 96 | B98: 96 | C98: 96 | D98: 10 (Ten) | E98: 50/- Each | F98: 500/- | G98: =H97+1 -> 951 | H98: =G98+9 -> 960 | I98: Shafikunnisha Abdul Latif Khan | O98: 10/07 | Q98: C.S. No. 364(Pt.), 365(Pt.),366(Pt.), Division Dadar, Naigaon, R. A. Kidwai Marg, Wadala, Mumbai - 400031.
A99: 97 | B99: 97 | C99: 97 | D99: 10 (Ten) | E99: 50/- Each | F99: 500/- | G99: =H98+1 -> 961 | H99: =G99+9 -> 970 | I99: Shakil Ahmed Abdul Latif Khan | O99: 10/08 | Q99: C.S. No. 364(Pt.), 365(Pt.),366(Pt.), Division Dadar, Naigaon, R. A. Kidwai Marg, Wadala, Mumbai - 400031.
A100: 98 | B100: 98 | C100: 98 | D100: 10 (Ten) | E100: 50/- Each | F100: 500/- | G100: =H99+1 -> 971 | H100: =G100+9 -> 980 | I100: Anthony John Fernandes | O100: 10/09 | Q100: C.S. No. 364(Pt.), 365(Pt.),366(Pt.), Division Dadar, Naigaon, R. A. Kidwai Marg, Wadala, Mumbai - 400031.
A101: 99 | B101: 99 | C101: 99 | D101: 10 (Ten) | E101: 50/- Each | F101: 500/- | G101: =H100+1 -> 981 | H101: =G101+9 -> 990 | I101: Jayshri Shankar Shinde | O101: 10/11 | Q101: C.S. No. 364(Pt.), 365(Pt.),366(Pt.), Division Dadar, Naigaon, R. A. Kidwai Marg, Wadala, Mumbai - 400031.
... A106: 104 | B106: 104 | C106: 104 | D106: 10 (Ten) | E106: 50/- Each | F106: 500/- | G106: =H105+1 -> 1031 | H106: =G106+9 -> 1040 | I106: Mohammed Shafique Siddique | O106: 11/06 | Q106: C.S. No. 364(Pt.), 365(Pt.),366(Pt.), Division Dadar, Naigaon, R. A. Kidwai Marg, Wadala, Mumbai - 400031.
A107: 105 | B107: 105 | C107: 105 | D107: 10 (Ten) | E107: 50/- Each | F107: 500/- | G107: =H106+1 -> 1041 | H107: =G107+9 -> 1050 | I107: Mairaj Ali Mohram Ali Khan, Imtiyaz Ali Khan, | J107: Afzal Ali Moharram Ali Khan, Abdul Rehman Moharram Ali Khan | K107: Imran Ali Moharram Ali Khan | O107: 11/07 | Q107: C.S. No. 364(Pt.), 365(Pt.),366(Pt.), Division Dadar, Naigaon, R. A. Kidwai Marg, Wadala, Mumbai - 400031.
A108: 106 | B108: 106 | C108: 106 | D108: 10 (Ten) | E108: 50/- Each | F108: 500/- | G108: =H107+1 -> 1051 | H108: =G108+9 -> 1060 | I108: Mohd Altaf Mohd Ishaque Rangari | O108: 11/09 | Q108: C.S. No. 364(Pt.), 365(Pt.),366(Pt.), Division Dadar, Naigaon, R. A. Kidwai Marg, Wadala, Mumbai - 400031.
A109: 107 | B109: 107 | C109: 107 | D109: 10 (Ten) | E109: 50/- Each | F109: 500/- | G109: =H108+1 -> 1061 | H109: =G109+9 -> 1070 | I109: Sayeeda Ishaque Rangari | O109: 11/10 | Q109: C.S. No. 364(Pt.), 365(Pt.),366(Pt.), Division Dadar, Naigaon, R. A. Kidwai Marg, Wadala, Mumbai - 400031.
A110: 108 | B110: 108 | C110: 108 | D110: 10 (Ten) | E110: 50/- Each | F110: 500/- | G110: =H109+1 -> 1071 | H110: =G110+9 -> 1080 | I110: Mohd Yakub Ishaque Rangari | O110: 11/11 | Q110: C.S. No. 364(Pt.), 365(Pt.),366(Pt.), Division Dadar, Naigaon, R. A. Kidwai Marg, Wadala, Mumbai - 400031.
A111: 109 | B111: 109 | C111: 109 | D111: 10 (Ten) | E111: 50/- Each | F111: 500/- | G111: =H110+1 -> 1081 | H111: =G111+9 -> 1090 | I111: Iram Sajid Ahmed Siddique | O111: 11/14 | Q111: C.S. No. 364(Pt.), 365(Pt.),366(Pt.), Division Dadar, Naigaon, R. A. Kidwai Marg, Wadala, Mumbai - 400031.
A112: 110 | B112: 110 | C112: 110 | D112: 10 (Ten) | E112: 50/- Each | F112: 500/- | G112: =H111+1 -> 1091 | H112: =G112+9 -> 1100 | I112: Imtiyaz Ahmed Anwar Hussain Siddique | O112: 12/02 | Q112: C.S. No. 364(Pt.), 365(Pt.),366(Pt.), Division Dadar, Naigaon, R. A. Kidwai Marg, Wadala, Mumbai - 400031.
A113: 111 | B113: 111 | C113: 111 | D113: 10 (Ten) | E113: 50/- Each | F113: 500/- | G113: =H112+1 -> 1101 | H113: =G113+9 -> 1110 | I113: Haroon Hussain Shaikh | O113: 12/03 | Q113: C.S. No. 364(Pt.), 365(Pt.),366(Pt.), Division Dadar, Naigaon, R. A. Kidwai Marg, Wadala, Mumbai - 400031.
A114: 112 | B114: 112 | C114: 112 | D114: 10 (Ten) | E114: 50/- Each | F114: 500/- | G114: =H113+1 -> 1111 | H114: =G114+9 -> 1120 | I114: Rangari Mohamed Kasam Mohamed Ibrahim | O114: 12/04 | Q114: C.S. No. 364(Pt.), 365(Pt.),366(Pt.), Division Dadar, Naigaon, R. A. Kidwai Marg, Wadala, Mumbai - 400031.
A115: 113 | B115: 113 | C115: 113 | D115: 10 (Ten) | E115: 50/- Each | F115: 500/- | G115: =H114+1 -> 1121 | H115: =G115+9 -> 1130 | I115: Mohammad Sabir Razabali Shaikh | O115: 12/05 | Q115: C.S. No. 364(Pt.), 365(Pt.),366(Pt.), Division Dadar, Naigaon, R. A. Kidwai Marg, Wadala, Mumbai - 400031.
A116: 114 | B116: 114 | C116: 114 | D116: 10 (Ten) | E116: 50/- Each | F116: 500/- | G116: =H115+1 -> 1131 | H116: =G116+9 -> 1140 | I116: Usman Abdul Wahab Khan | O116: 12/11 | Q116: C.S. No. 364(Pt.), 365(Pt.),366(Pt.), Division Dadar, Naigaon, R. A. Kidwai Marg, Wadala, Mumbai - 400031.
A117: 115 | B117: 115 | C117: 115 | D117: 10 (Ten) | E117: 50/- Each | F117: 500/- | G117: =H116+1 -> 1141 | H117: =G117+9 -> 1150 | I117: Kausar Mohammed Farooque Shaikh | O117: 13/01 | Q117: C.S. No. 364(Pt.), 365(Pt.),366(Pt.), Division Dadar, Naigaon, R. A. Kidwai Marg, Wadala, Mumbai - 400031.
A118: 116 | B118: 116 | C118: 116 | D118: 10 (Ten) | E118: 50/- Each | F118: 500/- | G118: =H117+1 -> 1151 | H118: =G118+9 -> 1160 | I118: Moin Nayeem Qureshi | O118: 13/02 | Q118: C.S. No. 364(Pt.), 365(Pt.),366(Pt.), Division Dadar, Naigaon, R. A. Kidwai Marg, Wadala, Mumbai - 400031.
A119: 117 | B119: 117 | C119: 117 | D119: 10 (Ten) | E119: 50/- Each | F119: 500/- | G119: =H118+1 -> 1161 | H119: =G119+9 -> 1170 | I119: Maqsood Ahmed Mohammed Zakki Rangari | O119: 13/03 | Q119: C.S. No. 364(Pt.), 365(Pt.),366(Pt.), Division Dadar, Naigaon, R. A. Kidwai Marg, Wadala, Mumbai - 400031.
... A131: 129 | B131: 129 | C131: 129 | D131: 10 (Ten) | E131: 50/- Each | F131: 500/- | G131: =H130+1 -> 1281 | H131: =G131+9 -> 1290 | I131: Noor Mohammed Sarfaraz Khan | O131: 14/08 | Q131: C.S. No. 364(Pt.), 365(Pt.),366(Pt.), Division Dadar, Naigaon, R. A. Kidwai Marg, Wadala, Mumbai - 400031.
A132: 130 | B132: 130 | C132: 130 | D132: 10 (Ten) | E132: 50/- Each | F132: 500/- | G132: =H131+1 -> 1291 | H132: =G132+9 -> 1300 | I132: Mohammed Iqbal Mohammed Yusuf Qureshi | J132: Shahnaz Mohammed Iqbal Qureshi | O132: 14/09 | Q132: C.S. No. 364(Pt.), 365(Pt.),366(Pt.), Division Dadar, Naigaon, R. A. Kidwai Marg, Wadala, Mumbai - 400031.
A133: 131 | B133: 131 | C133: 131 | D133: 10 (Ten) | E133: 50/- Each | F133: 500/- | G133: =H132+1 -> 1301 | H133: =G133+9 -> 1310 | I133: Mohd Aslam Taj Mohd Khan | O133: 14/10 | Q133: C.S. No. 364(Pt.), 365(Pt.),366(Pt.), Division Dadar, Naigaon, R. A. Kidwai Marg, Wadala, Mumbai - 400031.
A134: 132 | B134: 132 | C134: 132 | D134: 10 (Ten) | E134: 50/- Each | F134: 500/- | G134: =H133+1 -> 1311 | H134: =G134+9 -> 1320 | I134: Arifa Yusuf Shaikh | O134: 14/11 | Q134: C.S. No. 364(Pt.), 365(Pt.),366(Pt.), Division Dadar, Naigaon, R. A. Kidwai Marg, Wadala, Mumbai - 400031.
A135: 133 | B135: 133 | C135: 133 | D135: 10 (Ten) | E135: 50/- Each | F135: 500/- | G135: =H134+1 -> 1321 | H135: =G135+9 -> 1330 | I135: Aziz Fatma Hamid Ali Sayed | O135: 14/12 | Q135: C.S. No. 364(Pt.), 365(Pt.),366(Pt.), Division Dadar, Naigaon, R. A. Kidwai Marg, Wadala, Mumbai - 400031.
A136: 134 | B136: 134 | C136: 134 | D136: 10 (Ten) | E136: 50/- Each | F136: 500/- | G136: =H135+1 -> 1331 | H136: =G136+9 -> 1340 | I136: Azimuddin Nayeem Qureshi | O136: 14/13 | Q136: C.S. No. 364(Pt.), 365(Pt.),366(Pt.), Division Dadar, Naigaon, R. A. Kidwai Marg, Wadala, Mumbai - 400031.
A137: 135 | B137: 135 | C137: 135 | D137: 10 (Ten) | E137: 50/- Each | F137: 500/- | G137: =H136+1 -> 1341 | H137: =G137+9 -> 1350 | I137: Siddiqua Begum Shamshad Khan | O137: 14/14 | Q137: C.S. No. 364(Pt.), 365(Pt.),366(Pt.), Division Dadar, Naigaon, R. A. Kidwai Marg, Wadala, Mumbai - 400031.
A138: 136 | B138: 136 | C138: 136 | D138: 10 (Ten) | E138: 50/- Each | F138: 500/- | G138: =H137+1 -> 1351 | H138: =G138+9 -> 1360 | I138: Zakir Mohammad Ahmed Khan | O138: 14/16 | Q138: C.S. No. 364(Pt.), 365(Pt.),366(Pt.), Division Dadar, Naigaon, R. A. Kidwai Marg, Wadala, Mumbai - 400031.
A139: 137 | B139: 137 | C139: 137 | D139: 10 (Ten) | E139: 50/- Each | F139: 500/- | G139: =H138+1 -> 1361 | H139: =G139+9 -> 1370 | I139: Qayyum Ashique Khan | O139: SH-01 | Q139: C.S. No. 364(Pt.), 365(Pt.),366(Pt.), Division Dadar, Naigaon, R. A. Kidwai Marg, Wadala, Mumbai - 400031.
A140: 138 | B140: 138 | C140: 138 | D140: 10 (Ten) | E140: 50/- Each | F140: 500/- | G140: =H139+1 -> 1371 | H140: =G140+9 -> 1380 | I140: Musahid Raza Ashique Khan | O140: SH-02 | Q140: C.S. No. 364(Pt.), 365(Pt.),366(Pt.), Division Dadar, Naigaon, R. A. Kidwai Marg, Wadala, Mumbai - 400031.
A141: 139 | B141: 139 | C141: 139 | D141: 10 (Ten) | E141: 50/- Each | F141: 500/- | G141: =H140+1 -> 1381 | H141: =G141+9 -> 1390 | I141: Moin Nayeem Qureshi | O141: SH-04 | Q141: C.S. No. 364(Pt.), 365(Pt.),366(Pt.), Division Dadar, Naigaon, R. A. Kidwai Marg, Wadala, Mumbai - 400031.
A142: 140 | B142: 140 | C142: 140 | D142: 10 (Ten) | E142: 50/- Each | F142: 500/- | G142: =H141+1 -> 1391 | H142: =G142+9 -> 1400 | I142: Ashfaque Anwar Shaikh | O142: SH-05 | Q142: C.S. No. 364(Pt.), 365(Pt.),366(Pt.), Division Dadar, Naigaon, R. A. Kidwai Marg, Wadala, Mumbai - 400031.
A143: 141 | B143: 141 | C143: 141 | D143: 10 (Ten) | E143: 50/- Each | F143: 500/- | G143: =H142+1 -> 1401 | H143: =G143+9 -> 1410 | I143: Anjum Yasmeen Mohammed Hashim Khan | O143: SH-07 | Q143: C.S. No. 364(Pt.), 365(Pt.),366(Pt.), Division Dadar, Naigaon, R. A. Kidwai Marg, Wadala, Mumbai - 400031.
A144: 142 | B144: 142 | C144: 142 | D144: 10 (Ten) | E144: 50/- Each | F144: 500/- | G144: =H143+1 -> 1411 | H144: =G144+9 -> 1420 | I144: Memoona Mushtaque Khatri | O144: 4/05 | Q144: C.S. No. 364(Pt.), 365(Pt.),366(Pt.), Division Dadar, Naigaon, R. A. Kidwai Marg, Wadala, Mumbai - 400031.
... A154: 152 | B154: 152 | C154: 152 | D154: 10 (Ten) | E154: 50/- Each | F154: 500/- | G154: =H153+1 -> 1511 | H154: =G154+9 -> 1520 | I154: Molly Patrick D'souza | O154: 2/16 | Q154: C.S. No. 364(Pt.), 365(Pt.),366(Pt.), Division Dadar, Naigaon, R. A. Kidwai Marg, Wadala, Mumbai - 400031.
A155: 153 | B155: 153 | C155: 153 | D155: 10 (Ten) | E155: 50/- Each | F155: 500/- | G155: =H154+1 -> 1521 | H155: =G155+9 -> 1530 | I155: Parvez Mudassar Khan | J155: Sameer Mudassar Khan | K155: Imran Mudassar Khan | O155: 3/04 | Q155: C.S. No. 364(Pt.), 365(Pt.),366(Pt.), Division Dadar, Naigaon, R. A. Kidwai Marg, Wadala, Mumbai - 400031.
A156: 154 | B156: 154 | C156: 154 | D156: 10 (Ten) | E156: 50/- Each | F156: 500/- | G156: =H155+1 -> 1531 | H156: =G156+9 -> 1540 | I156: Mohammed Irfan Rangari | O156: 3/05 | Q156: C.S. No. 364(Pt.), 365(Pt.),366(Pt.), Division Dadar, Naigaon, R. A. Kidwai Marg, Wadala, Mumbai - 400031.
A157: 155 | B157: 155 | C157: 155 | D157: 10 (Ten) | E157: 50/- Each | F157: 500/- | G157: =H156+1 -> 1541 | H157: =G157+9 -> 1550 | I157: Mohammad Siddique Yusuf Mastan, Hameeda Yusuf Mastan | J157: Iliyas Yunus Mastan, Nadeem Umar Mastan | O157: 3/07 | Q157: C.S. No. 364(Pt.), 365(Pt.),366(Pt.), Division Dadar, Naigaon, R. A. Kidwai Marg, Wadala, Mumbai - 400031.
A158: 156 | B158: 156 | C158: 156 | D158: 10 (Ten) | E158: 50/- Each | F158: 500/- | G158: =H157+1 -> 1551 | H158: =G158+9 -> 1560 | I158: Amir Raju Khan | O158: 3/13 | Q158: C.S. No. 364(Pt.), 365(Pt.),366(Pt.), Division Dadar, Naigaon, R. A. Kidwai Marg, Wadala, Mumbai - 400031.
A159: 157 | B159: 157 | C159: 157 | D159: 10 (Ten) | E159: 50/- Each | F159: 500/- | G159: =H158+1 -> 1561 | H159: =G159+9 -> 1570 | I159: Abdul Hamid Ibrahim Mastan | O159: 3/14 | Q159: C.S. No. 364(Pt.), 365(Pt.),366(Pt.), Division Dadar, Naigaon, R. A. Kidwai Marg, Wadala, Mumbai - 400031.
A160: 158 | B160: 158 | C160: 158 | D160: 10 (Ten) | E160: 50/- Each | F160: 500/- | G160: =H159+1 -> 1571 | H160: =G160+9 -> 1580 | I160: Liyakat Hasam Shaikh | O160: 4/11 | Q160: C.S. No. 364(Pt.), 365(Pt.),366(Pt.), Division Dadar, Naigaon, R. A. Kidwai Marg, Wadala, Mumbai - 400031.
A161: 159 | B161: 159 | C161: 159 | D161: 10 (Ten) | E161: 50/- Each | F161: 500/- | G161: =H160+1 -> 1581 | H161: =G161+9 -> 1590 | I161: Kaniz Fatima Ashfaque Ahmed Khan | O161: 4/12 | Q161: C.S. No. 364(Pt.), 365(Pt.),366(Pt.), Division Dadar, Naigaon, R. A. Kidwai Marg, Wadala, Mumbai - 400031.
A162: 160 | B162: 160 | C162: 160 | D162: 10 (Ten) | E162: 50/- Each | F162: 500/- | G162: =H161+1 -> 1591 | H162: =G162+9 -> 1600 | I162: Razia Naeem Chippa | O162: 4/13 | Q162: C.S. No. 364(Pt.), 365(Pt.),366(Pt.), Division Dadar, Naigaon, R. A. Kidwai Marg, Wadala, Mumbai - 400031.
A163: 161 | B163: 161 | C163: 161 | D163: 10 (Ten) | E163: 50/- Each | F163: 500/- | G163: =H162+1 -> 1601 | H163: =G163+9 -> 1610 | I163: Mohammed Saalik Zakir Khan | O163: 5/02 | Q163: C.S. No. 364(Pt.), 365(Pt.),366(Pt.), Division Dadar, Naigaon, R. A. Kidwai Marg, Wadala, Mumbai - 400031.
A164: 162 | B164: 162 | C164: 162 | D164: 10 (Ten) | E164: 50/- Each | F164: 500/- | G164: =H163+1 -> 1611 | H164: =G164+9 -> 1620 | I164: Chippa Mahmud Hussain | O164: 5/06 | Q164: C.S. No. 364(Pt.), 365(Pt.),366(Pt.), Division Dadar, Naigaon, R. A. Kidwai Marg, Wadala, Mumbai - 400031.
A165: 163 | B165: 163 | C165: 163 | D165: 10 (Ten) | E165: 50/- Each | F165: 500/- | G165: =H164+1 -> 1621 | H165: =G165+9 -> 1630 | I165: Romould John Tixeira, Flora Neville Tixeira, Peter John Tixeira | J165: Anthony John Tixeira, Maria Wilfred Annunciation, Chester John Tixeira, | K165: Austin John Tixeira & Apoline Gilroy Tixeira | O165: 5/08 | Q165: C.S. No. 364(Pt.), 365(Pt.),366(Pt.), Division Dadar, Naigaon, R. A. Kidwai Marg, Wadala, Mumbai - 400031.
...

Sheet 03_Form_I
A1: Sr. No. | B1: Date of Admission | C1: Date of Payment of Entrance Fees | D1: Members Name Full | J1: Address Permanent | L1: Address Residential / Care of | M1: Occupation | N1: Age on the Date of Admission | O1: Nominee Name Full | U1: Date of Nomination | V1: Date of Cessation of Membership | W1: Reason for Cessation | X1: Remark | Y1: Particulars of Shares Held - Entry 1 | AJ1: Particulars of Shares Held - Entry 2 | AU1: Particulars of Shares Held - Entry 3 | BF1: Particulars of Shares Held - Entry 4 | BQ1: Particulars of Shares Held - Entry 5 | CB1: Particulars of Shares Transferred or Surrendered - Entry 1 | CK1: Particulars of Shares Transferred or Surrendered - Entry 2 | CT1: Particulars of Shares Transferred or Surrendered - Entry 3 | DC1: Particulars of Shares Transferred or Surrendered - Entry 4 | DL1: Particulars of Shares Transferred or Surrendered - Entry 5
D2: 1 | E2: 2 | F2: 3 | G2: 4 | H2: 5 | I2: 6 | J2: Flat/Room/Shop/Office/Gala No. | K2: Wing No. | L2: New Address / As Above | O2: 1 | P2: 2 | Q2: 3 | R2: 4 | S2: 5 | T2: 6 | Y2: Date | Z2: Cash Book Folio No. | AA2: Application | AB2: Allotment | AC2: Amount Received 1st Call | AD2: Amount Received 2nd Call | AE2: Total Amount Received | AF2: No. of Shares Held | AG2: Shares From | AH2: Shares To | AI2: Share Certificate No. | AJ2: Date | AK2: Cash Book Folio No. | AL2: Application | AM2: Allotment | AN2: Amount Received 1st Call | AO2: Amount Received 2nd Call | AP2: Total Amount Received | AQ2: No. of Shares Held | AR2: Shares From | AS2: Shares To | AT2: Share Certificate No. | AU2: Date | AV2: Cash Book Folio No. | AW2: Application | AX2: Allotment | AY2: Amount Received 1st Call | AZ2: Amount Received 2nd Call | BA2: Total Amount Received | BB2: No. of Shares Held | BC2: Shares From | BD2: Shares To | BE2: Share Certificate No. | BF2: Date | BG2: Cash Book Folio No. | BH2: Application | BI2: Allotment | BJ2: Amount Received 1st Call | BK2: Amount Received 2nd Call | BL2: Total Amount Received | BM2: No. of Shares Held | BN2: Shares From | BO2: Shares To | BP2: Share Certificate No. | BQ2: Date | BR2: Cash Book Folio No. | BS2: Application | BT2: Allotment | BU2: Amount Received 1st Call | BV2: Amount Received 2nd Call | BW2: Total Amount Received | BX2: No. of Shares Held | BY2: Shares From | BZ2: Shares To | CA2: Share Certificate No. | CB2: Date | CC2: Cash Book Folio No. | CD2: Transfer Date | CE2: Share Certificate No. Transferred | CF2: No. of Shares Transferred / Refunded | CG2: Balances - No. of Shares Held | CH2: Balances - Serial No. of Share Cert. | CI2: Amount Rs | CJ2: Amount P | CK2: Date | CL2: Cash Book Folio No. | CM2: Transfer Date | CN2: Share Certificate No. Transferred | CO2: No. of Shares Transferred / Refunded | CP2: Balances - No. of Shares Held | CQ2: Balances - Serial No. of Share Cert. | CR2: Amount Rs | CS2: Amount P | CT2: Date | CU2: Cash Book Folio No. | CV2: Transfer Date | CW2: Share Certificate No. Transferred | CX2: No. of Shares Transferred / Refunded | CY2: Balances - No. of Shares Held | CZ2: Balances - Serial No. of Share Cert. | DA2: Amount Rs | DB2: Amount P | DC2: Date | DD2: Cash Book Folio No. | DE2: Transfer Date | DF2: Share Certificate No. Transferred | DG2: No. of Shares Transferred / Refunded | DH2: Balances - No. of Shares Held | DI2: Balances - Serial No. of Share Cert. | DJ2: Amount Rs | DK2: Amount P | DL2: Date | DM2: Cash Book Folio No. | DN2: Transfer Date | DO2: Share Certificate No. Transferred | DP2: No. of Shares Transferred / Refunded | DQ2: Balances - No. of Shares Held | DR2: Balances - Serial No. of Share Cert. | DS2: Amount Rs | DT2: Amount P
A3: =IF('02_Common_Member_Master'!A3="","",'02_Common_Member_Master'!A3) -> 1 | D3: =IF('02_Common_Member_Master'!I3="","",'02_Common_Member_Master'!I3) -> Nafisha Khatoon Sharif Ahmed Khan | E3: =IF('02_Common_Member_Master'!J3="","",'02_Common_Member_Master'!J3) | F3: =IF('02_Common_Member_Master'!K3="","",'02_Common_Member_Master'!K3) | G3: =IF('02_Common_Member_Master'!L3="","",'02_Common_Member_Master'!L3) | H3: =IF('02_Common_Member_Master'!M3="","",'02_Common_Member_Master'!M3) | I3: =IF('02_Common_Member_Master'!N3="","",'02_Common_Member_Master'!N3) | J3: =IF('02_Common_Member_Master'!#REF!="","",'02_Common_Member_Master'!#REF!) -> #REF! | K3: =IF('02_Common_Member_Master'!#REF!="","",'02_Common_Member_Master'!#REF!) -> #REF! | L3: =IF('02_Common_Member_Master'!#REF!="","",'02_Common_Member_Master'!#REF!) -> #REF! | AF3: =IF('02_Common_Member_Master'!D3="","",'02_Common_Member_Master'!D3) -> 10 (Ten) | AG3: =IF('02_Common_Member_Master'!G3="","",'02_Common_Member_Master'!G3) -> 1 | AH3: =IF('02_Common_Member_Master'!H3="","",'02_Common_Member_Master'!H3) -> 10 | AI3: =IF('02_Common_Member_Master'!C3="","",'02_Common_Member_Master'!C3) -> 1
A4: =IF('02_Common_Member_Master'!A4="","",'02_Common_Member_Master'!A4) -> 2 | D4: =IF('02_Common_Member_Master'!I4="","",'02_Common_Member_Master'!I4) -> Azhar Husain Mazhar Husain Khan | E4: =IF('02_Common_Member_Master'!J4="","",'02_Common_Member_Master'!J4) | F4: =IF('02_Common_Member_Master'!K4="","",'02_Common_Member_Master'!K4) | G4: =IF('02_Common_Member_Master'!L4="","",'02_Common_Member_Master'!L4) | H4: =IF('02_Common_Member_Master'!M4="","",'02_Common_Member_Master'!M4) | I4: =IF('02_Common_Member_Master'!N4="","",'02_Common_Member_Master'!N4) | J4: ` | K4: =IF('02_Common_Member_Master'!#REF!="","",'02_Common_Member_Master'!#REF!) -> #REF! | L4: =IF('02_Common_Member_Master'!#REF!="","",'02_Common_Member_Master'!#REF!) -> #REF! | AF4: =IF('02_Common_Member_Master'!D4="","",'02_Common_Member_Master'!D4) -> 10 (Ten) | AG4: =IF('02_Common_Member_Master'!G4="","",'02_Common_Member_Master'!G4) -> 11 | AH4: =IF('02_Common_Member_Master'!H4="","",'02_Common_Member_Master'!H4) -> 20 | AI4: =IF('02_Common_Member_Master'!C4="","",'02_Common_Member_Master'!C4) -> 2
A5: =IF('02_Common_Member_Master'!A5="","",'02_Common_Member_Master'!A5) -> 3 | D5: =IF('02_Common_Member_Master'!I5="","",'02_Common_Member_Master'!I5) -> Abdul Malik Azhar Husain Khan | E5: =IF('02_Common_Member_Master'!J5="","",'02_Common_Member_Master'!J5) | F5: =IF('02_Common_Member_Master'!K5="","",'02_Common_Member_Master'!K5) | G5: =IF('02_Common_Member_Master'!L5="","",'02_Common_Member_Master'!L5) | H5: =IF('02_Common_Member_Master'!M5="","",'02_Common_Member_Master'!M5) | I5: =IF('02_Common_Member_Master'!N5="","",'02_Common_Member_Master'!N5) | J5: =IF('02_Common_Member_Master'!#REF!="","",'02_Common_Member_Master'!#REF!) -> #REF! | K5: =IF('02_Common_Member_Master'!#REF!="","",'02_Common_Member_Master'!#REF!) -> #REF! | L5: =IF('02_Common_Member_Master'!#REF!="","",'02_Common_Member_Master'!#REF!) -> #REF! | AF5: =IF('02_Common_Member_Master'!D5="","",'02_Common_Member_Master'!D5) -> 10 (Ten) | AG5: =IF('02_Common_Member_Master'!G5="","",'02_Common_Member_Master'!G5) -> 21 | AH5: =IF('02_Common_Member_Master'!H5="","",'02_Common_Member_Master'!H5) -> 30 | AI5: =IF('02_Common_Member_Master'!C5="","",'02_Common_Member_Master'!C5) -> 3
A6: =IF('02_Common_Member_Master'!A6="","",'02_Common_Member_Master'!A6) -> 4 | D6: =IF('02_Common_Member_Master'!I6="","",'02_Common_Member_Master'!I6) -> Abdul Wadood Abdul Mannan Sayyed | E6: =IF('02_Common_Member_Master'!J6="","",'02_Common_Member_Master'!J6) | F6: =IF('02_Common_Member_Master'!K6="","",'02_Common_Member_Master'!K6) | G6: =IF('02_Common_Member_Master'!L6="","",'02_Common_Member_Master'!L6) | H6: =IF('02_Common_Member_Master'!M6="","",'02_Common_Member_Master'!M6) | I6: =IF('02_Common_Member_Master'!N6="","",'02_Common_Member_Master'!N6) | J6: =IF('02_Common_Member_Master'!#REF!="","",'02_Common_Member_Master'!#REF!) -> #REF! | K6: =IF('02_Common_Member_Master'!#REF!="","",'02_Common_Member_Master'!#REF!) -> #REF! | L6: =IF('02_Common_Member_Master'!#REF!="","",'02_Common_Member_Master'!#REF!) -> #REF! | AF6: =IF('02_Common_Member_Master'!D6="","",'02_Common_Member_Master'!D6) -> 10 (Ten) | AG6: =IF('02_Common_Member_Master'!G6="","",'02_Common_Member_Master'!G6) -> 31 | AH6: =IF('02_Common_Member_Master'!H6="","",'02_Common_Member_Master'!H6) -> 40 | AI6: =IF('02_Common_Member_Master'!C6="","",'02_Common_Member_Master'!C6) -> 4
A7: =IF('02_Common_Member_Master'!A7="","",'02_Common_Member_Master'!A7) -> 5 | D7: =IF('02_Common_Member_Master'!I7="","",'02_Common_Member_Master'!I7) -> Abdulhai Abdul Mannan Sayyed | E7: =IF('02_Common_Member_Master'!J7="","",'02_Common_Member_Master'!J7) | F7: =IF('02_Common_Member_Master'!K7="","",'02_Common_Member_Master'!K7) | G7: =IF('02_Common_Member_Master'!L7="","",'02_Common_Member_Master'!L7) | H7: =IF('02_Common_Member_Master'!M7="","",'02_Common_Member_Master'!M7) | I7: =IF('02_Common_Member_Master'!N7="","",'02_Common_Member_Master'!N7) | J7: =IF('02_Common_Member_Master'!#REF!="","",'02_Common_Member_Master'!#REF!) -> #REF! | K7: =IF('02_Common_Member_Master'!#REF!="","",'02_Common_Member_Master'!#REF!) -> #REF! | L7: =IF('02_Common_Member_Master'!#REF!="","",'02_Common_Member_Master'!#REF!) -> #REF! | AF7: =IF('02_Common_Member_Master'!D7="","",'02_Common_Member_Master'!D7) -> 10 (Ten) | AG7: =IF('02_Common_Member_Master'!G7="","",'02_Common_Member_Master'!G7) -> 41 | AH7: =IF('02_Common_Member_Master'!H7="","",'02_Common_Member_Master'!H7) -> 50 | AI7: =IF('02_Common_Member_Master'!C7="","",'02_Common_Member_Master'!C7) -> 5
A8: =IF('02_Common_Member_Master'!A8="","",'02_Common_Member_Master'!A8) -> 6 | D8: =IF('02_Common_Member_Master'!I8="","",'02_Common_Member_Master'!I8) -> Shakeel Ahmed Nazir Ahmed Khan | E8: =IF('02_Common_Member_Master'!J8="","",'02_Common_Member_Master'!J8) | F8: =IF('02_Common_Member_Master'!K8="","",'02_Common_Member_Master'!K8) | G8: =IF('02_Common_Member_Master'!L8="","",'02_Common_Member_Master'!L8) | H8: =IF('02_Common_Member_Master'!M8="","",'02_Common_Member_Master'!M8) | I8: =IF('02_Common_Member_Master'!N8="","",'02_Common_Member_Master'!N8) | J8: =IF('02_Common_Member_Master'!#REF!="","",'02_Common_Member_Master'!#REF!) -> #REF! | K8: =IF('02_Common_Member_Master'!#REF!="","",'02_Common_Member_Master'!#REF!) -> #REF! | L8: =IF('02_Common_Member_Master'!#REF!="","",'02_Common_Member_Master'!#REF!) -> #REF! | AF8: =IF('02_Common_Member_Master'!D8="","",'02_Common_Member_Master'!D8) -> 10 (Ten) | AG8: =IF('02_Common_Member_Master'!G8="","",'02_Common_Member_Master'!G8) -> 51 | AH8: =IF('02_Common_Member_Master'!H8="","",'02_Common_Member_Master'!H8) -> 60 | AI8: =IF('02_Common_Member_Master'!C8="","",'02_Common_Member_Master'!C8) -> 6
A9: =IF('02_Common_Member_Master'!A9="","",'02_Common_Member_Master'!A9) -> 7 | D9: =IF('02_Common_Member_Master'!I9="","",'02_Common_Member_Master'!I9) -> Mohammed Nawaz Ramzan Ali Shaikh | E9: =IF('02_Common_Member_Master'!J9="","",'02_Common_Member_Master'!J9) | F9: =IF('02_Common_Member_Master'!K9="","",'02_Common_Member_Master'!K9) | G9: =IF('02_Common_Member_Master'!L9="","",'02_Common_Member_Master'!L9) | H9: =IF('02_Common_Member_Master'!M9="","",'02_Common_Member_Master'!M9) | I9: =IF('02_Common_Member_Master'!N9="","",'02_Common_Member_Master'!N9) | J9: =IF('02_Common_Member_Master'!#REF!="","",'02_Common_Member_Master'!#REF!) -> #REF! | K9: =IF('02_Common_Member_Master'!#REF!="","",'02_Common_Member_Master'!#REF!) -> #REF! | L9: =IF('02_Common_Member_Master'!#REF!="","",'02_Common_Member_Master'!#REF!) -> #REF! | AF9: =IF('02_Common_Member_Master'!D9="","",'02_Common_Member_Master'!D9) -> 10 (Ten) | AG9: =IF('02_Common_Member_Master'!G9="","",'02_Common_Member_Master'!G9) -> 61 | AH9: =IF('02_Common_Member_Master'!H9="","",'02_Common_Member_Master'!H9) -> 70 | AI9: =IF('02_Common_Member_Master'!C9="","",'02_Common_Member_Master'!C9) -> 7
A10: =IF('02_Common_Member_Master'!A10="","",'02_Common_Member_Master'!A10) -> 8 | D10: =IF('02_Common_Member_Master'!I10="","",'02_Common_Member_Master'!I10) -> Gulam Husain Kutbullah Khan | E10: =IF('02_Common_Member_Master'!J10="","",'02_Common_Member_Master'!J10) | F10: =IF('02_Common_Member_Master'!K10="","",'02_Common_Member_Master'!K10) | G10: =IF('02_Common_Member_Master'!L10="","",'02_Common_Member_Master'!L10) | H10: =IF('02_Common_Member_Master'!M10="","",'02_Common_Member_Master'!M10) | I10: =IF('02_Common_Member_Master'!N10="","",'02_Common_Member_Master'!N10) | J10: =IF('02_Common_Member_Master'!#REF!="","",'02_Common_Member_Master'!#REF!) -> #REF! | K10: =IF('02_Common_Member_Master'!#REF!="","",'02_Common_Member_Master'!#REF!) -> #REF! | L10: =IF('02_Common_Member_Master'!#REF!="","",'02_Common_Member_Master'!#REF!) -> #REF! | AF10: =IF('02_Common_Member_Master'!D10="","",'02_Common_Member_Master'!D10) -> 10 (Ten) | AG10: =IF('02_Common_Member_Master'!G10="","",'02_Common_Member_Master'!G10) -> 71 | AH10: =IF('02_Common_Member_Master'!H10="","",'02_Common_Member_Master'!H10) -> 80 | AI10: =IF('02_Common_Member_Master'!C10="","",'02_Common_Member_Master'!C10) -> 8
A11: =IF('02_Common_Member_Master'!A11="","",'02_Common_Member_Master'!A11) -> 9 | D11: =IF('02_Common_Member_Master'!I11="","",'02_Common_Member_Master'!I11) -> Sajid Azhar Husain Khan | E11: =IF('02_Common_Member_Master'!J11="","",'02_Common_Member_Master'!J11) | F11: =IF('02_Common_Member_Master'!K11="","",'02_Common_Member_Master'!K11) | G11: =IF('02_Common_Member_Master'!L11="","",'02_Common_Member_Master'!L11) | H11: =IF('02_Common_Member_Master'!M11="","",'02_Common_Member_Master'!M11) | I11: =IF('02_Common_Member_Master'!N11="","",'02_Common_Member_Master'!N11) | J11: =IF('02_Common_Member_Master'!#REF!="","",'02_Common_Member_Master'!#REF!) -> #REF! | K11: =IF('02_Common_Member_Master'!#REF!="","",'02_Common_Member_Master'!#REF!) -> #REF! | L11: =IF('02_Common_Member_Master'!#REF!="","",'02_Common_Member_Master'!#REF!) -> #REF! | AF11: =IF('02_Common_Member_Master'!D11="","",'02_Common_Member_Master'!D11) -> 10 (Ten) | AG11: =IF('02_Common_Member_Master'!G11="","",'02_Common_Member_Master'!G11) -> 81 | AH11: =IF('02_Common_Member_Master'!H11="","",'02_Common_Member_Master'!H11) -> 90 | AI11: =IF('02_Common_Member_Master'!C11="","",'02_Common_Member_Master'!C11) -> 9
A12: =IF('02_Common_Member_Master'!A12="","",'02_Common_Member_Master'!A12) -> 10 | D12: =IF('02_Common_Member_Master'!I12="","",'02_Common_Member_Master'!I12) -> Shakilabanoo Mohamed Iqbal Khan | E12: =IF('02_Common_Member_Master'!J12="","",'02_Common_Member_Master'!J12) | F12: =IF('02_Common_Member_Master'!K12="","",'02_Common_Member_Master'!K12) | G12: =IF('02_Common_Member_Master'!L12="","",'02_Common_Member_Master'!L12) | H12: =IF('02_Common_Member_Master'!M12="","",'02_Common_Member_Master'!M12) | I12: =IF('02_Common_Member_Master'!N12="","",'02_Common_Member_Master'!N12) | J12: =IF('02_Common_Member_Master'!#REF!="","",'02_Common_Member_Master'!#REF!) -> #REF! | K12: =IF('02_Common_Member_Master'!#REF!="","",'02_Common_Member_Master'!#REF!) -> #REF! | L12: =IF('02_Common_Member_Master'!#REF!="","",'02_Common_Member_Master'!#REF!) -> #REF! | AF12: =IF('02_Common_Member_Master'!D12="","",'02_Common_Member_Master'!D12) -> 10 (Ten) | AG12: =IF('02_Common_Member_Master'!G12="","",'02_Common_Member_Master'!G12) -> 91 | AH12: =IF('02_Common_Member_Master'!H12="","",'02_Common_Member_Master'!H12) -> 100 | AI12: =IF('02_Common_Member_Master'!C12="","",'02_Common_Member_Master'!C12) -> 10
A13: =IF('02_Common_Member_Master'!A13="","",'02_Common_Member_Master'!A13) -> 11 | D13: =IF('02_Common_Member_Master'!I13="","",'02_Common_Member_Master'!I13) -> Mohd Hashim Anwarul Haque Khan | E13: =IF('02_Common_Member_Master'!J13="","",'02_Common_Member_Master'!J13) | F13: =IF('02_Common_Member_Master'!K13="","",'02_Common_Member_Master'!K13) | G13: =IF('02_Common_Member_Master'!L13="","",'02_Common_Member_Master'!L13) | H13: =IF('02_Common_Member_Master'!M13="","",'02_Common_Member_Master'!M13) | I13: =IF('02_Common_Member_Master'!N13="","",'02_Common_Member_Master'!N13) | J13: =IF('02_Common_Member_Master'!#REF!="","",'02_Common_Member_Master'!#REF!) -> #REF! | K13: =IF('02_Common_Member_Master'!#REF!="","",'02_Common_Member_Master'!#REF!) -> #REF! | L13: =IF('02_Common_Member_Master'!#REF!="","",'02_Common_Member_Master'!#REF!) -> #REF! | AF13: =IF('02_Common_Member_Master'!D13="","",'02_Common_Member_Master'!D13) -> 10 (Ten) | AG13: =IF('02_Common_Member_Master'!G13="","",'02_Common_Member_Master'!G13) -> 101 | AH13: =IF('02_Common_Member_Master'!H13="","",'02_Common_Member_Master'!H13) -> 110 | AI13: =IF('02_Common_Member_Master'!C13="","",'02_Common_Member_Master'!C13) -> 11
A14: =IF('02_Common_Member_Master'!A14="","",'02_Common_Member_Master'!A14) -> 12 | D14: =IF('02_Common_Member_Master'!I14="","",'02_Common_Member_Master'!I14) -> Mohammed Shoyab Mohammed Faique Farooque | E14: =IF('02_Common_Member_Master'!J14="","",'02_Common_Member_Master'!J14) | F14: =IF('02_Common_Member_Master'!K14="","",'02_Common_Member_Master'!K14) | G14: =IF('02_Common_Member_Master'!L14="","",'02_Common_Member_Master'!L14) | H14: =IF('02_Common_Member_Master'!M14="","",'02_Common_Member_Master'!M14) | I14: =IF('02_Common_Member_Master'!N14="","",'02_Common_Member_Master'!N14) | J14: =IF('02_Common_Member_Master'!#REF!="","",'02_Common_Member_Master'!#REF!) -> #REF! | K14: =IF('02_Common_Member_Master'!#REF!="","",'02_Common_Member_Master'!#REF!) -> #REF! | L14: =IF('02_Common_Member_Master'!#REF!="","",'02_Common_Member_Master'!#REF!) -> #REF! | AF14: =IF('02_Common_Member_Master'!D14="","",'02_Common_Member_Master'!D14) -> 10 (Ten) | AG14: =IF('02_Common_Member_Master'!G14="","",'02_Common_Member_Master'!G14) -> 111 | AH14: =IF('02_Common_Member_Master'!H14="","",'02_Common_Member_Master'!H14) -> 120 | AI14: =IF('02_Common_Member_Master'!C14="","",'02_Common_Member_Master'!C14) -> 12
A15: =IF('02_Common_Member_Master'!A15="","",'02_Common_Member_Master'!A15) -> 13 | D15: =IF('02_Common_Member_Master'!I15="","",'02_Common_Member_Master'!I15) -> Ruksana Rashid Ahmed Khan | E15: =IF('02_Common_Member_Master'!J15="","",'02_Common_Member_Master'!J15) | F15: =IF('02_Common_Member_Master'!K15="","",'02_Common_Member_Master'!K15) | G15: =IF('02_Common_Member_Master'!L15="","",'02_Common_Member_Master'!L15) | H15: =IF('02_Common_Member_Master'!M15="","",'02_Common_Member_Master'!M15) | I15: =IF('02_Common_Member_Master'!N15="","",'02_Common_Member_Master'!N15) | J15: =IF('02_Common_Member_Master'!#REF!="","",'02_Common_Member_Master'!#REF!) -> #REF! | K15: =IF('02_Common_Member_Master'!#REF!="","",'02_Common_Member_Master'!#REF!) -> #REF! | L15: =IF('02_Common_Member_Master'!#REF!="","",'02_Common_Member_Master'!#REF!) -> #REF! | AF15: =IF('02_Common_Member_Master'!D15="","",'02_Common_Member_Master'!D15) -> 10 (Ten) | AG15: =IF('02_Common_Member_Master'!G15="","",'02_Common_Member_Master'!G15) -> 121 | AH15: =IF('02_Common_Member_Master'!H15="","",'02_Common_Member_Master'!H15) -> 130 | AI15: =IF('02_Common_Member_Master'!C15="","",'02_Common_Member_Master'!C15) -> 13
A16: =IF('02_Common_Member_Master'!A16="","",'02_Common_Member_Master'!A16) -> 14 | D16: =IF('02_Common_Member_Master'!I16="","",'02_Common_Member_Master'!I16) -> Mohd Akhtar Ramzan Khan | E16: =IF('02_Common_Member_Master'!J16="","",'02_Common_Member_Master'!J16) | F16: =IF('02_Common_Member_Master'!K16="","",'02_Common_Member_Master'!K16) | G16: =IF('02_Common_Member_Master'!L16="","",'02_Common_Member_Master'!L16) | H16: =IF('02_Common_Member_Master'!M16="","",'02_Common_Member_Master'!M16) | I16: =IF('02_Common_Member_Master'!N16="","",'02_Common_Member_Master'!N16) | J16: =IF('02_Common_Member_Master'!#REF!="","",'02_Common_Member_Master'!#REF!) -> #REF! | K16: =IF('02_Common_Member_Master'!#REF!="","",'02_Common_Member_Master'!#REF!) -> #REF! | L16: =IF('02_Common_Member_Master'!#REF!="","",'02_Common_Member_Master'!#REF!) -> #REF! | AF16: =IF('02_Common_Member_Master'!D16="","",'02_Common_Member_Master'!D16) -> 10 (Ten) | AG16: =IF('02_Common_Member_Master'!G16="","",'02_Common_Member_Master'!G16) -> 131 | AH16: =IF('02_Common_Member_Master'!H16="","",'02_Common_Member_Master'!H16) -> 140 | AI16: =IF('02_Common_Member_Master'!C16="","",'02_Common_Member_Master'!C16) -> 14
... A23: =IF('02_Common_Member_Master'!A23="","",'02_Common_Member_Master'!A23) -> 21 | D23: =IF('02_Common_Member_Master'!I23="","",'02_Common_Member_Master'!I23) -> Sarfaraz Israr Khan | E23: =IF('02_Common_Member_Master'!J23="","",'02_Common_Member_Master'!J23) | F23: =IF('02_Common_Member_Master'!K23="","",'02_Common_Member_Master'!K23) | G23: =IF('02_Common_Member_Master'!L23="","",'02_Common_Member_Master'!L23) | H23: =IF('02_Common_Member_Master'!M23="","",'02_Common_Member_Master'!M23) | I23: =IF('02_Common_Member_Master'!N23="","",'02_Common_Member_Master'!N23) | J23: =IF('02_Common_Member_Master'!#REF!="","",'02_Common_Member_Master'!#REF!) -> #REF! | K23: =IF('02_Common_Member_Master'!#REF!="","",'02_Common_Member_Master'!#REF!) -> #REF! | L23: =IF('02_Common_Member_Master'!#REF!="","",'02_Common_Member_Master'!#REF!) -> #REF! | AF23: =IF('02_Common_Member_Master'!D23="","",'02_Common_Member_Master'!D23) -> 10 (Ten) | AG23: =IF('02_Common_Member_Master'!G23="","",'02_Common_Member_Master'!G23) -> 201 | AH23: =IF('02_Common_Member_Master'!H23="","",'02_Common_Member_Master'!H23) -> 210 | AI23: =IF('02_Common_Member_Master'!C23="","",'02_Common_Member_Master'!C23) -> 21

Sheet 04_Form_J
A1: Sr. No. | B1: Members Name Full | H1: Permanent Address | J1: Class of Member
B2: 1 | C2: 2 | D2: 3 | E2: 4 | F2: 5 | G2: 6 | H2: Flat/Room/Shop/Office/Gala No. | I2: Wing No.
A3: =IF('02_Common_Member_Master'!A3="","",'02_Common_Member_Master'!A3) -> 1 | B3: =IF('02_Common_Member_Master'!I3="","",'02_Common_Member_Master'!I3) -> Nafisha Khatoon Sharif Ahmed Khan | C3: =IF('02_Common_Member_Master'!J3="","",'02_Common_Member_Master'!J3) | D3: =IF('02_Common_Member_Master'!K3="","",'02_Common_Member_Master'!K3) | E3: =IF('02_Common_Member_Master'!L3="","",'02_Common_Member_Master'!L3) | F3: =IF('02_Common_Member_Master'!M3="","",'02_Common_Member_Master'!M3) | G3: =IF('02_Common_Member_Master'!N3="","",'02_Common_Member_Master'!N3) | H3: =IF('02_Common_Member_Master'!#REF!="","",'02_Common_Member_Master'!#REF!) -> #REF! | I3: =IF('02_Common_Member_Master'!#REF!="","",'02_Common_Member_Master'!#REF!) -> #REF!
A4: =IF('02_Common_Member_Master'!A4="","",'02_Common_Member_Master'!A4) -> 2 | B4: =IF('02_Common_Member_Master'!I4="","",'02_Common_Member_Master'!I4) -> Azhar Husain Mazhar Husain Khan | C4: =IF('02_Common_Member_Master'!J4="","",'02_Common_Member_Master'!J4) | D4: =IF('02_Common_Member_Master'!K4="","",'02_Common_Member_Master'!K4) | E4: =IF('02_Common_Member_Master'!L4="","",'02_Common_Member_Master'!L4) | F4: =IF('02_Common_Member_Master'!M4="","",'02_Common_Member_Master'!M4) | G4: =IF('02_Common_Member_Master'!N4="","",'02_Common_Member_Master'!N4) | H4: =IF('02_Common_Member_Master'!#REF!="","",'02_Common_Member_Master'!#REF!) -> #REF! | I4: =IF('02_Common_Member_Master'!#REF!="","",'02_Common_Member_Master'!#REF!) -> #REF!
A5: =IF('02_Common_Member_Master'!A5="","",'02_Common_Member_Master'!A5) -> 3 | B5: =IF('02_Common_Member_Master'!I5="","",'02_Common_Member_Master'!I5) -> Abdul Malik Azhar Husain Khan | C5: =IF('02_Common_Member_Master'!J5="","",'02_Common_Member_Master'!J5) | D5: =IF('02_Common_Member_Master'!K5="","",'02_Common_Member_Master'!K5) | E5: =IF('02_Common_Member_Master'!L5="","",'02_Common_Member_Master'!L5) | F5: =IF('02_Common_Member_Master'!M5="","",'02_Common_Member_Master'!M5) | G5: =IF('02_Common_Member_Master'!N5="","",'02_Common_Member_Master'!N5) | H5: =IF('02_Common_Member_Master'!#REF!="","",'02_Common_Member_Master'!#REF!) -> #REF! | I5: =IF('02_Common_Member_Master'!#REF!="","",'02_Common_Member_Master'!#REF!) -> #REF!
A6: =IF('02_Common_Member_Master'!A6="","",'02_Common_Member_Master'!A6) -> 4 | B6: =IF('02_Common_Member_Master'!I6="","",'02_Common_Member_Master'!I6) -> Abdul Wadood Abdul Mannan Sayyed | C6: =IF('02_Common_Member_Master'!J6="","",'02_Common_Member_Master'!J6) | D6: =IF('02_Common_Member_Master'!K6="","",'02_Common_Member_Master'!K6) | E6: =IF('02_Common_Member_Master'!L6="","",'02_Common_Member_Master'!L6) | F6: =IF('02_Common_Member_Master'!M6="","",'02_Common_Member_Master'!M6) | G6: =IF('02_Common_Member_Master'!N6="","",'02_Common_Member_Master'!N6) | H6: =IF('02_Common_Member_Master'!#REF!="","",'02_Common_Member_Master'!#REF!) -> #REF! | I6: =IF('02_Common_Member_Master'!#REF!="","",'02_Common_Member_Master'!#REF!) -> #REF!
A7: =IF('02_Common_Member_Master'!A7="","",'02_Common_Member_Master'!A7) -> 5 | B7: =IF('02_Common_Member_Master'!I7="","",'02_Common_Member_Master'!I7) -> Abdulhai Abdul Mannan Sayyed | C7: =IF('02_Common_Member_Master'!J7="","",'02_Common_Member_Master'!J7) | D7: =IF('02_Common_Member_Master'!K7="","",'02_Common_Member_Master'!K7) | E7: =IF('02_Common_Member_Master'!L7="","",'02_Common_Member_Master'!L7) | F7: =IF('02_Common_Member_Master'!M7="","",'02_Common_Member_Master'!M7) | G7: =IF('02_Common_Member_Master'!N7="","",'02_Common_Member_Master'!N7) | H7: =IF('02_Common_Member_Master'!#REF!="","",'02_Common_Member_Master'!#REF!) -> #REF! | I7: =IF('02_Common_Member_Master'!#REF!="","",'02_Common_Member_Master'!#REF!) -> #REF!
A8: =IF('02_Common_Member_Master'!A8="","",'02_Common_Member_Master'!A8) -> 6 | B8: =IF('02_Common_Member_Master'!I8="","",'02_Common_Member_Master'!I8) -> Shakeel Ahmed Nazir Ahmed Khan | C8: =IF('02_Common_Member_Master'!J8="","",'02_Common_Member_Master'!J8) | D8: =IF('02_Common_Member_Master'!K8="","",'02_Common_Member_Master'!K8) | E8: =IF('02_Common_Member_Master'!L8="","",'02_Common_Member_Master'!L8) | F8: =IF('02_Common_Member_Master'!M8="","",'02_Common_Member_Master'!M8) | G8: =IF('02_Common_Member_Master'!N8="","",'02_Common_Member_Master'!N8) | H8: =IF('02_Common_Member_Master'!#REF!="","",'02_Common_Member_Master'!#REF!) -> #REF! | I8: =IF('02_Common_Member_Master'!#REF!="","",'02_Common_Member_Master'!#REF!) -> #REF!
A9: =IF('02_Common_Member_Master'!A9="","",'02_Common_Member_Master'!A9) -> 7 | B9: =IF('02_Common_Member_Master'!I9="","",'02_Common_Member_Master'!I9) -> Mohammed Nawaz Ramzan Ali Shaikh | C9: =IF('02_Common_Member_Master'!J9="","",'02_Common_Member_Master'!J9) | D9: =IF('02_Common_Member_Master'!K9="","",'02_Common_Member_Master'!K9) | E9: =IF('02_Common_Member_Master'!L9="","",'02_Common_Member_Master'!L9) | F9: =IF('02_Common_Member_Master'!M9="","",'02_Common_Member_Master'!M9) | G9: =IF('02_Common_Member_Master'!N9="","",'02_Common_Member_Master'!N9) | H9: =IF('02_Common_Member_Master'!#REF!="","",'02_Common_Member_Master'!#REF!) -> #REF! | I9: =IF('02_Common_Member_Master'!#REF!="","",'02_Common_Member_Master'!#REF!) -> #REF!
A10: =IF('02_Common_Member_Master'!A10="","",'02_Common_Member_Master'!A10) -> 8 | B10: =IF('02_Common_Member_Master'!I10="","",'02_Common_Member_Master'!I10) -> Gulam Husain Kutbullah Khan | C10: =IF('02_Common_Member_Master'!J10="","",'02_Common_Member_Master'!J10) | D10: =IF('02_Common_Member_Master'!K10="","",'02_Common_Member_Master'!K10) | E10: =IF('02_Common_Member_Master'!L10="","",'02_Common_Member_Master'!L10) | F10: =IF('02_Common_Member_Master'!M10="","",'02_Common_Member_Master'!M10) | G10: =IF('02_Common_Member_Master'!N10="","",'02_Common_Member_Master'!N10) | H10: =IF('02_Common_Member_Master'!#REF!="","",'02_Common_Member_Master'!#REF!) -> #REF! | I10: =IF('02_Common_Member_Master'!#REF!="","",'02_Common_Member_Master'!#REF!) -> #REF!
A11: =IF('02_Common_Member_Master'!A11="","",'02_Common_Member_Master'!A11) -> 9 | B11: =IF('02_Common_Member_Master'!I11="","",'02_Common_Member_Master'!I11) -> Sajid Azhar Husain Khan | C11: =IF('02_Common_Member_Master'!J11="","",'02_Common_Member_Master'!J11) | D11: =IF('02_Common_Member_Master'!K11="","",'02_Common_Member_Master'!K11) | E11: =IF('02_Common_Member_Master'!L11="","",'02_Common_Member_Master'!L11) | F11: =IF('02_Common_Member_Master'!M11="","",'02_Common_Member_Master'!M11) | G11: =IF('02_Common_Member_Master'!N11="","",'02_Common_Member_Master'!N11) | H11: =IF('02_Common_Member_Master'!#REF!="","",'02_Common_Member_Master'!#REF!) -> #REF! | I11: =IF('02_Common_Member_Master'!#REF!="","",'02_Common_Member_Master'!#REF!) -> #REF!
A12: =IF('02_Common_Member_Master'!A12="","",'02_Common_Member_Master'!A12) -> 10 | B12: =IF('02_Common_Member_Master'!I12="","",'02_Common_Member_Master'!I12) -> Shakilabanoo Mohamed Iqbal Khan | C12: =IF('02_Common_Member_Master'!J12="","",'02_Common_Member_Master'!J12) | D12: =IF('02_Common_Member_Master'!K12="","",'02_Common_Member_Master'!K12) | E12: =IF('02_Common_Member_Master'!L12="","",'02_Common_Member_Master'!L12) | F12: =IF('02_Common_Member_Master'!M12="","",'02_Common_Member_Master'!M12) | G12: =IF('02_Common_Member_Master'!N12="","",'02_Common_Member_Master'!N12) | H12: =IF('02_Common_Member_Master'!#REF!="","",'02_Common_Member_Master'!#REF!) -> #REF! | I12: =IF('02_Common_Member_Master'!#REF!="","",'02_Common_Member_Master'!#REF!) -> #REF!
A13: =IF('02_Common_Member_Master'!A13="","",'02_Common_Member_Master'!A13) -> 11 | B13: =IF('02_Common_Member_Master'!I13="","",'02_Common_Member_Master'!I13) -> Mohd Hashim Anwarul Haque Khan | C13: =IF('02_Common_Member_Master'!J13="","",'02_Common_Member_Master'!J13) | D13: =IF('02_Common_Member_Master'!K13="","",'02_Common_Member_Master'!K13) | E13: =IF('02_Common_Member_Master'!L13="","",'02_Common_Member_Master'!L13) | F13: =IF('02_Common_Member_Master'!M13="","",'02_Common_Member_Master'!M13) | G13: =IF('02_Common_Member_Master'!N13="","",'02_Common_Member_Master'!N13) | H13: =IF('02_Common_Member_Master'!#REF!="","",'02_Common_Member_Master'!#REF!) -> #REF! | I13: =IF('02_Common_Member_Master'!#REF!="","",'02_Common_Member_Master'!#REF!) -> #REF!
A14: =IF('02_Common_Member_Master'!A14="","",'02_Common_Member_Master'!A14) -> 12 | B14: =IF('02_Common_Member_Master'!I14="","",'02_Common_Member_Master'!I14) -> Mohammed Shoyab Mohammed Faique Farooque | C14: =IF('02_Common_Member_Master'!J14="","",'02_Common_Member_Master'!J14) | D14: =IF('02_Common_Member_Master'!K14="","",'02_Common_Member_Master'!K14) | E14: =IF('02_Common_Member_Master'!L14="","",'02_Common_Member_Master'!L14) | F14: =IF('02_Common_Member_Master'!M14="","",'02_Common_Member_Master'!M14) | G14: =IF('02_Common_Member_Master'!N14="","",'02_Common_Member_Master'!N14) | H14: =IF('02_Common_Member_Master'!#REF!="","",'02_Common_Member_Master'!#REF!) -> #REF! | I14: =IF('02_Common_Member_Master'!#REF!="","",'02_Common_Member_Master'!#REF!) -> #REF!
... A23: =IF('02_Common_Member_Master'!A23="","",'02_Common_Member_Master'!A23) -> 21 | B23: =IF('02_Common_Member_Master'!I23="","",'02_Common_Member_Master'!I23) -> Sarfaraz Israr Khan | C23: =IF('02_Common_Member_Master'!J23="","",'02_Common_Member_Master'!J23) | D23: =IF('02_Common_Member_Master'!K23="","",'02_Common_Member_Master'!K23) | E23: =IF('02_Common_Member_Master'!L23="","",'02_Common_Member_Master'!L23) | F23: =IF('02_Common_Member_Master'!M23="","",'02_Common_Member_Master'!M23) | G23: =IF('02_Common_Member_Master'!N23="","",'02_Common_Member_Master'!N23) | H23: =IF('02_Common_Member_Master'!#REF!="","",'02_Common_Member_Master'!#REF!) -> #REF! | I23: =IF('02_Common_Member_Master'!#REF!="","",'02_Common_Member_Master'!#REF!) -> #REF!

Sheet 05_Share_Register
A1: Sr. No. | B1: Date of allotment of Share | C1: Cash Book folio No. | D1: Share Certificate No. | E1: No. of Shares | F1: Value of One Share | G1: Value of Shares | H1: Address | J1: Members Name Full | P1: Details of Shares Transferred or Refunded
H2: Flat/Room/Shop/Office/Gala No. | I2: Wing No. | J2: 1 | K2: 2 | L2: 3 | M2: 4 | N2: 5 | O2: 6 | P2: Date of transfer / refund | Q2: Cash Book Journal Folio No. | R2: No. of Shares Transferred/Refunded From | S2: No. of Shares Transferred/Refunded To | T2: Share Certificate No. transferred or refunded | U2: Share Value transferred or refunded Rs. | V2: Name of the transferee or person receiving refund | W2: Authority for transfer or refund | X2: Remark
A3: =IF('02_Common_Member_Master'!A3="","",'02_Common_Member_Master'!A3) -> 1 | D3: =IF('02_Common_Member_Master'!C3="","",'02_Common_Member_Master'!C3) -> 1 | E3: =IF('02_Common_Member_Master'!D3="","",'02_Common_Member_Master'!D3) -> 10 (Ten) | F3: =IF('02_Common_Member_Master'!E3="","",'02_Common_Member_Master'!E3) -> 50/- Each | G3: =IF('02_Common_Member_Master'!F3="","",'02_Common_Member_Master'!F3) -> 500/- | H3: =IF('02_Common_Member_Master'!#REF!="","",'02_Common_Member_Master'!#REF!) -> #REF! | I3: =IF('02_Common_Member_Master'!#REF!="","",'02_Common_Member_Master'!#REF!) -> #REF! | J3: =IF('02_Common_Member_Master'!I3="","",'02_Common_Member_Master'!I3) -> Nafisha Khatoon Sharif Ahmed Khan | K3: =IF('02_Common_Member_Master'!J3="","",'02_Common_Member_Master'!J3) | L3: =IF('02_Common_Member_Master'!K3="","",'02_Common_Member_Master'!K3) | M3: =IF('02_Common_Member_Master'!L3="","",'02_Common_Member_Master'!L3) | N3: =IF('02_Common_Member_Master'!M3="","",'02_Common_Member_Master'!M3) | O3: =IF('02_Common_Member_Master'!N3="","",'02_Common_Member_Master'!N3)
A4: =IF('02_Common_Member_Master'!A4="","",'02_Common_Member_Master'!A4) -> 2 | D4: =IF('02_Common_Member_Master'!C4="","",'02_Common_Member_Master'!C4) -> 2 | E4: =IF('02_Common_Member_Master'!D4="","",'02_Common_Member_Master'!D4) -> 10 (Ten) | F4: =IF('02_Common_Member_Master'!E4="","",'02_Common_Member_Master'!E4) -> 50/- Each | G4: =IF('02_Common_Member_Master'!F4="","",'02_Common_Member_Master'!F4) -> 500/- | H4: =IF('02_Common_Member_Master'!#REF!="","",'02_Common_Member_Master'!#REF!) -> #REF! | I4: =IF('02_Common_Member_Master'!#REF!="","",'02_Common_Member_Master'!#REF!) -> #REF! | J4: =IF('02_Common_Member_Master'!I4="","",'02_Common_Member_Master'!I4) -> Azhar Husain Mazhar Husain Khan | K4: =IF('02_Common_Member_Master'!J4="","",'02_Common_Member_Master'!J4) | L4: =IF('02_Common_Member_Master'!K4="","",'02_Common_Member_Master'!K4) | M4: =IF('02_Common_Member_Master'!L4="","",'02_Common_Member_Master'!L4) | N4: =IF('02_Common_Member_Master'!M4="","",'02_Common_Member_Master'!M4) | O4: =IF('02_Common_Member_Master'!N4="","",'02_Common_Member_Master'!N4)
A5: =IF('02_Common_Member_Master'!A5="","",'02_Common_Member_Master'!A5) -> 3 | D5: =IF('02_Common_Member_Master'!C5="","",'02_Common_Member_Master'!C5) -> 3 | E5: =IF('02_Common_Member_Master'!D5="","",'02_Common_Member_Master'!D5) -> 10 (Ten) | F5: =IF('02_Common_Member_Master'!E5="","",'02_Common_Member_Master'!E5) -> 50/- Each | G5: =IF('02_Common_Member_Master'!F5="","",'02_Common_Member_Master'!F5) -> 500/- | H5: =IF('02_Common_Member_Master'!#REF!="","",'02_Common_Member_Master'!#REF!) -> #REF! | I5: =IF('02_Common_Member_Master'!#REF!="","",'02_Common_Member_Master'!#REF!) -> #REF! | J5: =IF('02_Common_Member_Master'!I5="","",'02_Common_Member_Master'!I5) -> Abdul Malik Azhar Husain Khan | K5: =IF('02_Common_Member_Master'!J5="","",'02_Common_Member_Master'!J5) | L5: =IF('02_Common_Member_Master'!K5="","",'02_Common_Member_Master'!K5) | M5: =IF('02_Common_Member_Master'!L5="","",'02_Common_Member_Master'!L5) | N5: =IF('02_Common_Member_Master'!M5="","",'02_Common_Member_Master'!M5) | O5: =IF('02_Common_Member_Master'!N5="","",'02_Common_Member_Master'!N5)
A6: =IF('02_Common_Member_Master'!A6="","",'02_Common_Member_Master'!A6) -> 4 | D6: =IF('02_Common_Member_Master'!C6="","",'02_Common_Member_Master'!C6) -> 4 | E6: =IF('02_Common_Member_Master'!D6="","",'02_Common_Member_Master'!D6) -> 10 (Ten) | F6: =IF('02_Common_Member_Master'!E6="","",'02_Common_Member_Master'!E6) -> 50/- Each | G6: =IF('02_Common_Member_Master'!F6="","",'02_Common_Member_Master'!F6) -> 500/- | H6: =IF('02_Common_Member_Master'!#REF!="","",'02_Common_Member_Master'!#REF!) -> #REF! | I6: =IF('02_Common_Member_Master'!#REF!="","",'02_Common_Member_Master'!#REF!) -> #REF! | J6: =IF('02_Common_Member_Master'!I6="","",'02_Common_Member_Master'!I6) -> Abdul Wadood Abdul Mannan Sayyed | K6: =IF('02_Common_Member_Master'!J6="","",'02_Common_Member_Master'!J6) | L6: =IF('02_Common_Member_Master'!K6="","",'02_Common_Member_Master'!K6) | M6: =IF('02_Common_Member_Master'!L6="","",'02_Common_Member_Master'!L6) | N6: =IF('02_Common_Member_Master'!M6="","",'02_Common_Member_Master'!M6) | O6: =IF('02_Common_Member_Master'!N6="","",'02_Common_Member_Master'!N6)
A7: =IF('02_Common_Member_Master'!A7="","",'02_Common_Member_Master'!A7) -> 5 | D7: =IF('02_Common_Member_Master'!C7="","",'02_Common_Member_Master'!C7) -> 5 | E7: =IF('02_Common_Member_Master'!D7="","",'02_Common_Member_Master'!D7) -> 10 (Ten) | F7: =IF('02_Common_Member_Master'!E7="","",'02_Common_Member_Master'!E7) -> 50/- Each | G7: =IF('02_Common_Member_Master'!F7="","",'02_Common_Member_Master'!F7) -> 500/- | H7: =IF('02_Common_Member_Master'!#REF!="","",'02_Common_Member_Master'!#REF!) -> #REF! | I7: =IF('02_Common_Member_Master'!#REF!="","",'02_Common_Member_Master'!#REF!) -> #REF! | J7: =IF('02_Common_Member_Master'!I7="","",'02_Common_Member_Master'!I7) -> Abdulhai Abdul Mannan Sayyed | K7: =IF('02_Common_Member_Master'!J7="","",'02_Common_Member_Master'!J7) | L7: =IF('02_Common_Member_Master'!K7="","",'02_Common_Member_Master'!K7) | M7: =IF('02_Common_Member_Master'!L7="","",'02_Common_Member_Master'!L7) | N7: =IF('02_Common_Member_Master'!M7="","",'02_Common_Member_Master'!M7) | O7: =IF('02_Common_Member_Master'!N7="","",'02_Common_Member_Master'!N7)
A8: =IF('02_Common_Member_Master'!A8="","",'02_Common_Member_Master'!A8) -> 6 | D8: =IF('02_Common_Member_Master'!C8="","",'02_Common_Member_Master'!C8) -> 6 | E8: =IF('02_Common_Member_Master'!D8="","",'02_Common_Member_Master'!D8) -> 10 (Ten) | F8: =IF('02_Common_Member_Master'!E8="","",'02_Common_Member_Master'!E8) -> 50/- Each | G8: =IF('02_Common_Member_Master'!F8="","",'02_Common_Member_Master'!F8) -> 500/- | H8: =IF('02_Common_Member_Master'!#REF!="","",'02_Common_Member_Master'!#REF!) -> #REF! | I8: =IF('02_Common_Member_Master'!#REF!="","",'02_Common_Member_Master'!#REF!) -> #REF! | J8: =IF('02_Common_Member_Master'!I8="","",'02_Common_Member_Master'!I8) -> Shakeel Ahmed Nazir Ahmed Khan | K8: =IF('02_Common_Member_Master'!J8="","",'02_Common_Member_Master'!J8) | L8: =IF('02_Common_Member_Master'!K8="","",'02_Common_Member_Master'!K8) | M8: =IF('02_Common_Member_Master'!L8="","",'02_Common_Member_Master'!L8) | N8: =IF('02_Common_Member_Master'!M8="","",'02_Common_Member_Master'!M8) | O8: =IF('02_Common_Member_Master'!N8="","",'02_Common_Member_Master'!N8)
A9: =IF('02_Common_Member_Master'!A9="","",'02_Common_Member_Master'!A9) -> 7 | D9: =IF('02_Common_Member_Master'!C9="","",'02_Common_Member_Master'!C9) -> 7 | E9: =IF('02_Common_Member_Master'!D9="","",'02_Common_Member_Master'!D9) -> 10 (Ten) | F9: =IF('02_Common_Member_Master'!E9="","",'02_Common_Member_Master'!E9) -> 50/- Each | G9: =IF('02_Common_Member_Master'!F9="","",'02_Common_Member_Master'!F9) -> 500/- | H9: =IF('02_Common_Member_Master'!#REF!="","",'02_Common_Member_Master'!#REF!) -> #REF! | I9: =IF('02_Common_Member_Master'!#REF!="","",'02_Common_Member_Master'!#REF!) -> #REF! | J9: =IF('02_Common_Member_Master'!I9="","",'02_Common_Member_Master'!I9) -> Mohammed Nawaz Ramzan Ali Shaikh | K9: =IF('02_Common_Member_Master'!J9="","",'02_Common_Member_Master'!J9) | L9: =IF('02_Common_Member_Master'!K9="","",'02_Common_Member_Master'!K9) | M9: =IF('02_Common_Member_Master'!L9="","",'02_Common_Member_Master'!L9) | N9: =IF('02_Common_Member_Master'!M9="","",'02_Common_Member_Master'!M9) | O9: =IF('02_Common_Member_Master'!N9="","",'02_Common_Member_Master'!N9)
A10: =IF('02_Common_Member_Master'!A10="","",'02_Common_Member_Master'!A10) -> 8 | D10: =IF('02_Common_Member_Master'!C10="","",'02_Common_Member_Master'!C10) -> 8 | E10: =IF('02_Common_Member_Master'!D10="","",'02_Common_Member_Master'!D10) -> 10 (Ten) | F10: =IF('02_Common_Member_Master'!E10="","",'02_Common_Member_Master'!E10) -> 50/- Each | G10: =IF('02_Common_Member_Master'!F10="","",'02_Common_Member_Master'!F10) -> 500/- | H10: =IF('02_Common_Member_Master'!#REF!="","",'02_Common_Member_Master'!#REF!) -> #REF! | I10: =IF('02_Common_Member_Master'!#REF!="","",'02_Common_Member_Master'!#REF!) -> #REF! | J10: =IF('02_Common_Member_Master'!I10="","",'02_Common_Member_Master'!I10) -> Gulam Husain Kutbullah Khan | K10: =IF('02_Common_Member_Master'!J10="","",'02_Common_Member_Master'!J10) | L10: =IF('02_Common_Member_Master'!K10="","",'02_Common_Member_Master'!K10) | M10: =IF('02_Common_Member_Master'!L10="","",'02_Common_Member_Master'!L10) | N10: =IF('02_Common_Member_Master'!M10="","",'02_Common_Member_Master'!M10) | O10: =IF('02_Common_Member_Master'!N10="","",'02_Common_Member_Master'!N10)
A11: =IF('02_Common_Member_Master'!A11="","",'02_Common_Member_Master'!A11) -> 9 | D11: =IF('02_Common_Member_Master'!C11="","",'02_Common_Member_Master'!C11) -> 9 | E11: =IF('02_Common_Member_Master'!D11="","",'02_Common_Member_Master'!D11) -> 10 (Ten) | F11: =IF('02_Common_Member_Master'!E11="","",'02_Common_Member_Master'!E11) -> 50/- Each | G11: =IF('02_Common_Member_Master'!F11="","",'02_Common_Member_Master'!F11) -> 500/- | H11: =IF('02_Common_Member_Master'!#REF!="","",'02_Common_Member_Master'!#REF!) -> #REF! | I11: =IF('02_Common_Member_Master'!#REF!="","",'02_Common_Member_Master'!#REF!) -> #REF! | J11: =IF('02_Common_Member_Master'!I11="","",'02_Common_Member_Master'!I11) -> Sajid Azhar Husain Khan | K11: =IF('02_Common_Member_Master'!J11="","",'02_Common_Member_Master'!J11) | L11: =IF('02_Common_Member_Master'!K11="","",'02_Common_Member_Master'!K11) | M11: =IF('02_Common_Member_Master'!L11="","",'02_Common_Member_Master'!L11) | N11: =IF('02_Common_Member_Master'!M11="","",'02_Common_Member_Master'!M11) | O11: =IF('02_Common_Member_Master'!N11="","",'02_Common_Member_Master'!N11)
A12: =IF('02_Common_Member_Master'!A12="","",'02_Common_Member_Master'!A12) -> 10 | D12: =IF('02_Common_Member_Master'!C12="","",'02_Common_Member_Master'!C12) -> 10 | E12: =IF('02_Common_Member_Master'!D12="","",'02_Common_Member_Master'!D12) -> 10 (Ten) | F12: =IF('02_Common_Member_Master'!E12="","",'02_Common_Member_Master'!E12) -> 50/- Each | G12: =IF('02_Common_Member_Master'!F12="","",'02_Common_Member_Master'!F12) -> 500/- | H12: =IF('02_Common_Member_Master'!#REF!="","",'02_Common_Member_Master'!#REF!) -> #REF! | I12: =IF('02_Common_Member_Master'!#REF!="","",'02_Common_Member_Master'!#REF!) -> #REF! | J12: =IF('02_Common_Member_Master'!I12="","",'02_Common_Member_Master'!I12) -> Shakilabanoo Mohamed Iqbal Khan | K12: =IF('02_Common_Member_Master'!J12="","",'02_Common_Member_Master'!J12) | L12: =IF('02_Common_Member_Master'!K12="","",'02_Common_Member_Master'!K12) | M12: =IF('02_Common_Member_Master'!L12="","",'02_Common_Member_Master'!L12) | N12: =IF('02_Common_Member_Master'!M12="","",'02_Common_Member_Master'!M12) | O12: =IF('02_Common_Member_Master'!N12="","",'02_Common_Member_Master'!N12)
A13: =IF('02_Common_Member_Master'!A13="","",'02_Common_Member_Master'!A13) -> 11 | D13: =IF('02_Common_Member_Master'!C13="","",'02_Common_Member_Master'!C13) -> 11 | E13: =IF('02_Common_Member_Master'!D13="","",'02_Common_Member_Master'!D13) -> 10 (Ten) | F13: =IF('02_Common_Member_Master'!E13="","",'02_Common_Member_Master'!E13) -> 50/- Each | G13: =IF('02_Common_Member_Master'!F13="","",'02_Common_Member_Master'!F13) -> 500/- | H13: =IF('02_Common_Member_Master'!#REF!="","",'02_Common_Member_Master'!#REF!) -> #REF! | I13: =IF('02_Common_Member_Master'!#REF!="","",'02_Common_Member_Master'!#REF!) -> #REF! | J13: =IF('02_Common_Member_Master'!I13="","",'02_Common_Member_Master'!I13) -> Mohd Hashim Anwarul Haque Khan | K13: =IF('02_Common_Member_Master'!J13="","",'02_Common_Member_Master'!J13) | L13: =IF('02_Common_Member_Master'!K13="","",'02_Common_Member_Master'!K13) | M13: =IF('02_Common_Member_Master'!L13="","",'02_Common_Member_Master'!L13) | N13: =IF('02_Common_Member_Master'!M13="","",'02_Common_Member_Master'!M13) | O13: =IF('02_Common_Member_Master'!N13="","",'02_Common_Member_Master'!N13)
A14: =IF('02_Common_Member_Master'!A14="","",'02_Common_Member_Master'!A14) -> 12 | D14: =IF('02_Common_Member_Master'!C14="","",'02_Common_Member_Master'!C14) -> 12 | E14: =IF('02_Common_Member_Master'!D14="","",'02_Common_Member_Master'!D14) -> 10 (Ten) | F14: =IF('02_Common_Member_Master'!E14="","",'02_Common_Member_Master'!E14) -> 50/- Each | G14: =IF('02_Common_Member_Master'!F14="","",'02_Common_Member_Master'!F14) -> 500/- | H14: =IF('02_Common_Member_Master'!#REF!="","",'02_Common_Member_Master'!#REF!) -> #REF! | I14: =IF('02_Common_Member_Master'!#REF!="","",'02_Common_Member_Master'!#REF!) -> #REF! | J14: =IF('02_Common_Member_Master'!I14="","",'02_Common_Member_Master'!I14) -> Mohammed Shoyab Mohammed Faique Farooque | K14: =IF('02_Common_Member_Master'!J14="","",'02_Common_Member_Master'!J14) | L14: =IF('02_Common_Member_Master'!K14="","",'02_Common_Member_Master'!K14) | M14: =IF('02_Common_Member_Master'!L14="","",'02_Common_Member_Master'!L14) | N14: =IF('02_Common_Member_Master'!M14="","",'02_Common_Member_Master'!M14) | O14: =IF('02_Common_Member_Master'!N14="","",'02_Common_Member_Master'!N14)
... A23: =IF('02_Common_Member_Master'!A23="","",'02_Common_Member_Master'!A23) -> 21 | D23: =IF('02_Common_Member_Master'!C23="","",'02_Common_Member_Master'!C23) -> 21 | E23: =IF('02_Common_Member_Master'!D23="","",'02_Common_Member_Master'!D23) -> 10 (Ten) | F23: =IF('02_Common_Member_Master'!E23="","",'02_Common_Member_Master'!E23) -> 50/- Each | G23: =IF('02_Common_Member_Master'!F23="","",'02_Common_Member_Master'!F23) -> 500/- | H23: =IF('02_Common_Member_Master'!#REF!="","",'02_Common_Member_Master'!#REF!) -> #REF! | I23: =IF('02_Common_Member_Master'!#REF!="","",'02_Common_Member_Master'!#REF!) -> #REF! | J23: =IF('02_Common_Member_Master'!I23="","",'02_Common_Member_Master'!I23) -> Sarfaraz Israr Khan | K23: =IF('02_Common_Member_Master'!J23="","",'02_Common_Member_Master'!J23) | L23: =IF('02_Common_Member_Master'!K23="","",'02_Common_Member_Master'!K23) | M23: =IF('02_Common_Member_Master'!L23="","",'02_Common_Member_Master'!L23) | N23: =IF('02_Common_Member_Master'!M23="","",'02_Common_Member_Master'!M23) | O23: =IF('02_Common_Member_Master'!N23="","",'02_Common_Member_Master'!N23)

Sheet 06_Nomination_Register
A1: Sr. No. | B1: Member Name | H1: Flat / Wing | J1: Date of Nomination | K1: Name/s of Nominee/s & Addresses of the Nominee/s | Q1: Percentage % | W1: Managing Committee Meeting Date | X1: Revocation Date | Y1: Remarks
B2: 1 | C2: 2 | D2: 3 | E2: 4 | F2: 5 | G2: 6 | H2: Flat No. | I2: Wing No. | K2: 1 | L2: 2 | M2: 3 | N2: 4 | O2: 5 | P2: 6 | Q2: 1 | R2: 2 | S2: 3 | T2: 4 | U2: 5 | V2: 6
A3: =IF('02_Common_Member_Master'!A3="","",'02_Common_Member_Master'!A3) -> 1 | B3: =IF('02_Common_Member_Master'!I3="","",'02_Common_Member_Master'!I3) -> Nafisha Khatoon Sharif Ahmed Khan | C3: =IF('02_Common_Member_Master'!J3="","",'02_Common_Member_Master'!J3) | D3: =IF('02_Common_Member_Master'!K3="","",'02_Common_Member_Master'!K3) | E3: =IF('02_Common_Member_Master'!L3="","",'02_Common_Member_Master'!L3) | F3: =IF('02_Common_Member_Master'!M3="","",'02_Common_Member_Master'!M3) | G3: =IF('02_Common_Member_Master'!N3="","",'02_Common_Member_Master'!N3) | H3: =IF('02_Common_Member_Master'!#REF!="","",'02_Common_Member_Master'!#REF!) -> #REF! | I3: =IF('02_Common_Member_Master'!#REF!="","",'02_Common_Member_Master'!#REF!) -> #REF!
A4: =IF('02_Common_Member_Master'!A4="","",'02_Common_Member_Master'!A4) -> 2 | B4: =IF('02_Common_Member_Master'!I4="","",'02_Common_Member_Master'!I4) -> Azhar Husain Mazhar Husain Khan | C4: =IF('02_Common_Member_Master'!J4="","",'02_Common_Member_Master'!J4) | D4: =IF('02_Common_Member_Master'!K4="","",'02_Common_Member_Master'!K4) | E4: =IF('02_Common_Member_Master'!L4="","",'02_Common_Member_Master'!L4) | F4: =IF('02_Common_Member_Master'!M4="","",'02_Common_Member_Master'!M4) | G4: =IF('02_Common_Member_Master'!N4="","",'02_Common_Member_Master'!N4) | H4: =IF('02_Common_Member_Master'!#REF!="","",'02_Common_Member_Master'!#REF!) -> #REF! | I4: =IF('02_Common_Member_Master'!#REF!="","",'02_Common_Member_Master'!#REF!) -> #REF!
A5: =IF('02_Common_Member_Master'!A5="","",'02_Common_Member_Master'!A5) -> 3 | B5: =IF('02_Common_Member_Master'!I5="","",'02_Common_Member_Master'!I5) -> Abdul Malik Azhar Husain Khan | C5: =IF('02_Common_Member_Master'!J5="","",'02_Common_Member_Master'!J5) | D5: =IF('02_Common_Member_Master'!K5="","",'02_Common_Member_Master'!K5) | E5: =IF('02_Common_Member_Master'!L5="","",'02_Common_Member_Master'!L5) | F5: =IF('02_Common_Member_Master'!M5="","",'02_Common_Member_Master'!M5) | G5: =IF('02_Common_Member_Master'!N5="","",'02_Common_Member_Master'!N5) | H5: =IF('02_Common_Member_Master'!#REF!="","",'02_Common_Member_Master'!#REF!) -> #REF! | I5: =IF('02_Common_Member_Master'!#REF!="","",'02_Common_Member_Master'!#REF!) -> #REF!
A6: =IF('02_Common_Member_Master'!A6="","",'02_Common_Member_Master'!A6) -> 4 | B6: =IF('02_Common_Member_Master'!I6="","",'02_Common_Member_Master'!I6) -> Abdul Wadood Abdul Mannan Sayyed | C6: =IF('02_Common_Member_Master'!J6="","",'02_Common_Member_Master'!J6) | D6: =IF('02_Common_Member_Master'!K6="","",'02_Common_Member_Master'!K6) | E6: =IF('02_Common_Member_Master'!L6="","",'02_Common_Member_Master'!L6) | F6: =IF('02_Common_Member_Master'!M6="","",'02_Common_Member_Master'!M6) | G6: =IF('02_Common_Member_Master'!N6="","",'02_Common_Member_Master'!N6) | H6: =IF('02_Common_Member_Master'!#REF!="","",'02_Common_Member_Master'!#REF!) -> #REF! | I6: =IF('02_Common_Member_Master'!#REF!="","",'02_Common_Member_Master'!#REF!) -> #REF!
A7: =IF('02_Common_Member_Master'!A7="","",'02_Common_Member_Master'!A7) -> 5 | B7: =IF('02_Common_Member_Master'!I7="","",'02_Common_Member_Master'!I7) -> Abdulhai Abdul Mannan Sayyed | C7: =IF('02_Common_Member_Master'!J7="","",'02_Common_Member_Master'!J7) | D7: =IF('02_Common_Member_Master'!K7="","",'02_Common_Member_Master'!K7) | E7: =IF('02_Common_Member_Master'!L7="","",'02_Common_Member_Master'!L7) | F7: =IF('02_Common_Member_Master'!M7="","",'02_Common_Member_Master'!M7) | G7: =IF('02_Common_Member_Master'!N7="","",'02_Common_Member_Master'!N7) | H7: =IF('02_Common_Member_Master'!#REF!="","",'02_Common_Member_Master'!#REF!) -> #REF! | I7: =IF('02_Common_Member_Master'!#REF!="","",'02_Common_Member_Master'!#REF!) -> #REF!
A8: =IF('02_Common_Member_Master'!A8="","",'02_Common_Member_Master'!A8) -> 6 | B8: =IF('02_Common_Member_Master'!I8="","",'02_Common_Member_Master'!I8) -> Shakeel Ahmed Nazir Ahmed Khan | C8: =IF('02_Common_Member_Master'!J8="","",'02_Common_Member_Master'!J8) | D8: =IF('02_Common_Member_Master'!K8="","",'02_Common_Member_Master'!K8) | E8: =IF('02_Common_Member_Master'!L8="","",'02_Common_Member_Master'!L8) | F8: =IF('02_Common_Member_Master'!M8="","",'02_Common_Member_Master'!M8) | G8: =IF('02_Common_Member_Master'!N8="","",'02_Common_Member_Master'!N8) | H8: =IF('02_Common_Member_Master'!#REF!="","",'02_Common_Member_Master'!#REF!) -> #REF! | I8: =IF('02_Common_Member_Master'!#REF!="","",'02_Common_Member_Master'!#REF!) -> #REF!
A9: =IF('02_Common_Member_Master'!A9="","",'02_Common_Member_Master'!A9) -> 7 | B9: =IF('02_Common_Member_Master'!I9="","",'02_Common_Member_Master'!I9) -> Mohammed Nawaz Ramzan Ali Shaikh | C9: =IF('02_Common_Member_Master'!J9="","",'02_Common_Member_Master'!J9) | D9: =IF('02_Common_Member_Master'!K9="","",'02_Common_Member_Master'!K9) | E9: =IF('02_Common_Member_Master'!L9="","",'02_Common_Member_Master'!L9) | F9: =IF('02_Common_Member_Master'!M9="","",'02_Common_Member_Master'!M9) | G9: =IF('02_Common_Member_Master'!N9="","",'02_Common_Member_Master'!N9) | H9: =IF('02_Common_Member_Master'!#REF!="","",'02_Common_Member_Master'!#REF!) -> #REF! | I9: =IF('02_Common_Member_Master'!#REF!="","",'02_Common_Member_Master'!#REF!) -> #REF!
A10: =IF('02_Common_Member_Master'!A10="","",'02_Common_Member_Master'!A10) -> 8 | B10: =IF('02_Common_Member_Master'!I10="","",'02_Common_Member_Master'!I10) -> Gulam Husain Kutbullah Khan | C10: =IF('02_Common_Member_Master'!J10="","",'02_Common_Member_Master'!J10) | D10: =IF('02_Common_Member_Master'!K10="","",'02_Common_Member_Master'!K10) | E10: =IF('02_Common_Member_Master'!L10="","",'02_Common_Member_Master'!L10) | F10: =IF('02_Common_Member_Master'!M10="","",'02_Common_Member_Master'!M10) | G10: =IF('02_Common_Member_Master'!N10="","",'02_Common_Member_Master'!N10) | H10: =IF('02_Common_Member_Master'!#REF!="","",'02_Common_Member_Master'!#REF!) -> #REF! | I10: =IF('02_Common_Member_Master'!#REF!="","",'02_Common_Member_Master'!#REF!) -> #REF!
A11: =IF('02_Common_Member_Master'!A11="","",'02_Common_Member_Master'!A11) -> 9 | B11: =IF('02_Common_Member_Master'!I11="","",'02_Common_Member_Master'!I11) -> Sajid Azhar Husain Khan | C11: =IF('02_Common_Member_Master'!J11="","",'02_Common_Member_Master'!J11) | D11: =IF('02_Common_Member_Master'!K11="","",'02_Common_Member_Master'!K11) | E11: =IF('02_Common_Member_Master'!L11="","",'02_Common_Member_Master'!L11) | F11: =IF('02_Common_Member_Master'!M11="","",'02_Common_Member_Master'!M11) | G11: =IF('02_Common_Member_Master'!N11="","",'02_Common_Member_Master'!N11) | H11: =IF('02_Common_Member_Master'!#REF!="","",'02_Common_Member_Master'!#REF!) -> #REF! | I11: =IF('02_Common_Member_Master'!#REF!="","",'02_Common_Member_Master'!#REF!) -> #REF!
A12: =IF('02_Common_Member_Master'!A12="","",'02_Common_Member_Master'!A12) -> 10 | B12: =IF('02_Common_Member_Master'!I12="","",'02_Common_Member_Master'!I12) -> Shakilabanoo Mohamed Iqbal Khan | C12: =IF('02_Common_Member_Master'!J12="","",'02_Common_Member_Master'!J12) | D12: =IF('02_Common_Member_Master'!K12="","",'02_Common_Member_Master'!K12) | E12: =IF('02_Common_Member_Master'!L12="","",'02_Common_Member_Master'!L12) | F12: =IF('02_Common_Member_Master'!M12="","",'02_Common_Member_Master'!M12) | G12: =IF('02_Common_Member_Master'!N12="","",'02_Common_Member_Master'!N12) | H12: =IF('02_Common_Member_Master'!#REF!="","",'02_Common_Member_Master'!#REF!) -> #REF! | I12: =IF('02_Common_Member_Master'!#REF!="","",'02_Common_Member_Master'!#REF!) -> #REF!
A13: =IF('02_Common_Member_Master'!A13="","",'02_Common_Member_Master'!A13) -> 11 | B13: =IF('02_Common_Member_Master'!I13="","",'02_Common_Member_Master'!I13) -> Mohd Hashim Anwarul Haque Khan | C13: =IF('02_Common_Member_Master'!J13="","",'02_Common_Member_Master'!J13) | D13: =IF('02_Common_Member_Master'!K13="","",'02_Common_Member_Master'!K13) | E13: =IF('02_Common_Member_Master'!L13="","",'02_Common_Member_Master'!L13) | F13: =IF('02_Common_Member_Master'!M13="","",'02_Common_Member_Master'!M13) | G13: =IF('02_Common_Member_Master'!N13="","",'02_Common_Member_Master'!N13) | H13: =IF('02_Common_Member_Master'!#REF!="","",'02_Common_Member_Master'!#REF!) -> #REF! | I13: =IF('02_Common_Member_Master'!#REF!="","",'02_Common_Member_Master'!#REF!) -> #REF!
A14: =IF('02_Common_Member_Master'!A14="","",'02_Common_Member_Master'!A14) -> 12 | B14: =IF('02_Common_Member_Master'!I14="","",'02_Common_Member_Master'!I14) -> Mohammed Shoyab Mohammed Faique Farooque | C14: =IF('02_Common_Member_Master'!J14="","",'02_Common_Member_Master'!J14) | D14: =IF('02_Common_Member_Master'!K14="","",'02_Common_Member_Master'!K14) | E14: =IF('02_Common_Member_Master'!L14="","",'02_Common_Member_Master'!L14) | F14: =IF('02_Common_Member_Master'!M14="","",'02_Common_Member_Master'!M14) | G14: =IF('02_Common_Member_Master'!N14="","",'02_Common_Member_Master'!N14) | H14: =IF('02_Common_Member_Master'!#REF!="","",'02_Common_Member_Master'!#REF!) -> #REF! | I14: =IF('02_Common_Member_Master'!#REF!="","",'02_Common_Member_Master'!#REF!) -> #REF!
... A23: =IF('02_Common_Member_Master'!A23="","",'02_Common_Member_Master'!A23) -> 21 | B23: =IF('02_Common_Member_Master'!I23="","",'02_Common_Member_Master'!I23) -> Sarfaraz Israr Khan | C23: =IF('02_Common_Member_Master'!J23="","",'02_Common_Member_Master'!J23) | D23: =IF('02_Common_Member_Master'!K23="","",'02_Common_Member_Master'!K23) | E23: =IF('02_Common_Member_Master'!L23="","",'02_Common_Member_Master'!L23) | F23: =IF('02_Common_Member_Master'!M23="","",'02_Common_Member_Master'!M23) | G23: =IF('02_Common_Member_Master'!N23="","",'02_Common_Member_Master'!N23) | H23: =IF('02_Common_Member_Master'!#REF!="","",'02_Common_Member_Master'!#REF!) -> #REF! | I23: =IF('02_Common_Member_Master'!#REF!="","",'02_Common_Member_Master'!#REF!) -> #REF!

Sheet 07_Property_Register
A1: Sr. No. | B1: Name of Co-partner Member | H1: Date of Possession | I1: Distinguishing No. of Tenement | K1: Description of Tenement | L1: Area of Tenement | M1: Cost of Tenement | O1: Annual Ground Rent Rs. | P1: Date of Cessation of Membership | Q1: Signature Chairman / Hon. Secretary | R1: Remarks (Reason of Cessation / Transfer to Sr. No. and Date)
B2: 1 | C2: 2 | D2: 3 | E2: 4 | F2: 5 | G2: 6 | I2: Flat No. | J2: Floor No. | M2: Land Rs. | N2: Const. Rs.
A3: =IF('02_Common_Member_Master'!A3="","",'02_Common_Member_Master'!A3) -> 1 | B3: =IF('02_Common_Member_Master'!I3="","",'02_Common_Member_Master'!I3) -> Nafisha Khatoon Sharif Ahmed Khan | C3: =IF('02_Common_Member_Master'!J3="","",'02_Common_Member_Master'!J3) | D3: =IF('02_Common_Member_Master'!K3="","",'02_Common_Member_Master'!K3) | E3: =IF('02_Common_Member_Master'!L3="","",'02_Common_Member_Master'!L3) | F3: =IF('02_Common_Member_Master'!M3="","",'02_Common_Member_Master'!M3) | G3: =IF('02_Common_Member_Master'!N3="","",'02_Common_Member_Master'!N3) | I3: =IF('02_Common_Member_Master'!#REF!="","",'02_Common_Member_Master'!#REF!) -> #REF!
A4: =IF('02_Common_Member_Master'!A4="","",'02_Common_Member_Master'!A4) -> 2 | B4: =IF('02_Common_Member_Master'!I4="","",'02_Common_Member_Master'!I4) -> Azhar Husain Mazhar Husain Khan | C4: =IF('02_Common_Member_Master'!J4="","",'02_Common_Member_Master'!J4) | D4: =IF('02_Common_Member_Master'!K4="","",'02_Common_Member_Master'!K4) | E4: =IF('02_Common_Member_Master'!L4="","",'02_Common_Member_Master'!L4) | F4: =IF('02_Common_Member_Master'!M4="","",'02_Common_Member_Master'!M4) | G4: =IF('02_Common_Member_Master'!N4="","",'02_Common_Member_Master'!N4) | I4: =IF('02_Common_Member_Master'!#REF!="","",'02_Common_Member_Master'!#REF!) -> #REF!
A5: =IF('02_Common_Member_Master'!A5="","",'02_Common_Member_Master'!A5) -> 3 | B5: =IF('02_Common_Member_Master'!I5="","",'02_Common_Member_Master'!I5) -> Abdul Malik Azhar Husain Khan | C5: =IF('02_Common_Member_Master'!J5="","",'02_Common_Member_Master'!J5) | D5: =IF('02_Common_Member_Master'!K5="","",'02_Common_Member_Master'!K5) | E5: =IF('02_Common_Member_Master'!L5="","",'02_Common_Member_Master'!L5) | F5: =IF('02_Common_Member_Master'!M5="","",'02_Common_Member_Master'!M5) | G5: =IF('02_Common_Member_Master'!N5="","",'02_Common_Member_Master'!N5) | I5: =IF('02_Common_Member_Master'!#REF!="","",'02_Common_Member_Master'!#REF!) -> #REF!
A6: =IF('02_Common_Member_Master'!A6="","",'02_Common_Member_Master'!A6) -> 4 | B6: =IF('02_Common_Member_Master'!I6="","",'02_Common_Member_Master'!I6) -> Abdul Wadood Abdul Mannan Sayyed | C6: =IF('02_Common_Member_Master'!J6="","",'02_Common_Member_Master'!J6) | D6: =IF('02_Common_Member_Master'!K6="","",'02_Common_Member_Master'!K6) | E6: =IF('02_Common_Member_Master'!L6="","",'02_Common_Member_Master'!L6) | F6: =IF('02_Common_Member_Master'!M6="","",'02_Common_Member_Master'!M6) | G6: =IF('02_Common_Member_Master'!N6="","",'02_Common_Member_Master'!N6) | I6: =IF('02_Common_Member_Master'!#REF!="","",'02_Common_Member_Master'!#REF!) -> #REF!
A7: =IF('02_Common_Member_Master'!A7="","",'02_Common_Member_Master'!A7) -> 5 | B7: =IF('02_Common_Member_Master'!I7="","",'02_Common_Member_Master'!I7) -> Abdulhai Abdul Mannan Sayyed | C7: =IF('02_Common_Member_Master'!J7="","",'02_Common_Member_Master'!J7) | D7: =IF('02_Common_Member_Master'!K7="","",'02_Common_Member_Master'!K7) | E7: =IF('02_Common_Member_Master'!L7="","",'02_Common_Member_Master'!L7) | F7: =IF('02_Common_Member_Master'!M7="","",'02_Common_Member_Master'!M7) | G7: =IF('02_Common_Member_Master'!N7="","",'02_Common_Member_Master'!N7) | I7: =IF('02_Common_Member_Master'!#REF!="","",'02_Common_Member_Master'!#REF!) -> #REF!
A8: =IF('02_Common_Member_Master'!A8="","",'02_Common_Member_Master'!A8) -> 6 | B8: =IF('02_Common_Member_Master'!I8="","",'02_Common_Member_Master'!I8) -> Shakeel Ahmed Nazir Ahmed Khan | C8: =IF('02_Common_Member_Master'!J8="","",'02_Common_Member_Master'!J8) | D8: =IF('02_Common_Member_Master'!K8="","",'02_Common_Member_Master'!K8) | E8: =IF('02_Common_Member_Master'!L8="","",'02_Common_Member_Master'!L8) | F8: =IF('02_Common_Member_Master'!M8="","",'02_Common_Member_Master'!M8) | G8: =IF('02_Common_Member_Master'!N8="","",'02_Common_Member_Master'!N8) | I8: =IF('02_Common_Member_Master'!#REF!="","",'02_Common_Member_Master'!#REF!) -> #REF!
A9: =IF('02_Common_Member_Master'!A9="","",'02_Common_Member_Master'!A9) -> 7 | B9: =IF('02_Common_Member_Master'!I9="","",'02_Common_Member_Master'!I9) -> Mohammed Nawaz Ramzan Ali Shaikh | C9: =IF('02_Common_Member_Master'!J9="","",'02_Common_Member_Master'!J9) | D9: =IF('02_Common_Member_Master'!K9="","",'02_Common_Member_Master'!K9) | E9: =IF('02_Common_Member_Master'!L9="","",'02_Common_Member_Master'!L9) | F9: =IF('02_Common_Member_Master'!M9="","",'02_Common_Member_Master'!M9) | G9: =IF('02_Common_Member_Master'!N9="","",'02_Common_Member_Master'!N9) | I9: =IF('02_Common_Member_Master'!#REF!="","",'02_Common_Member_Master'!#REF!) -> #REF!
A10: =IF('02_Common_Member_Master'!A10="","",'02_Common_Member_Master'!A10) -> 8 | B10: =IF('02_Common_Member_Master'!I10="","",'02_Common_Member_Master'!I10) -> Gulam Husain Kutbullah Khan | C10: =IF('02_Common_Member_Master'!J10="","",'02_Common_Member_Master'!J10) | D10: =IF('02_Common_Member_Master'!K10="","",'02_Common_Member_Master'!K10) | E10: =IF('02_Common_Member_Master'!L10="","",'02_Common_Member_Master'!L10) | F10: =IF('02_Common_Member_Master'!M10="","",'02_Common_Member_Master'!M10) | G10: =IF('02_Common_Member_Master'!N10="","",'02_Common_Member_Master'!N10) | I10: =IF('02_Common_Member_Master'!#REF!="","",'02_Common_Member_Master'!#REF!) -> #REF!
A11: =IF('02_Common_Member_Master'!A11="","",'02_Common_Member_Master'!A11) -> 9 | B11: =IF('02_Common_Member_Master'!I11="","",'02_Common_Member_Master'!I11) -> Sajid Azhar Husain Khan | C11: =IF('02_Common_Member_Master'!J11="","",'02_Common_Member_Master'!J11) | D11: =IF('02_Common_Member_Master'!K11="","",'02_Common_Member_Master'!K11) | E11: =IF('02_Common_Member_Master'!L11="","",'02_Common_Member_Master'!L11) | F11: =IF('02_Common_Member_Master'!M11="","",'02_Common_Member_Master'!M11) | G11: =IF('02_Common_Member_Master'!N11="","",'02_Common_Member_Master'!N11) | I11: =IF('02_Common_Member_Master'!#REF!="","",'02_Common_Member_Master'!#REF!) -> #REF!
A12: =IF('02_Common_Member_Master'!A12="","",'02_Common_Member_Master'!A12) -> 10 | B12: =IF('02_Common_Member_Master'!I12="","",'02_Common_Member_Master'!I12) -> Shakilabanoo Mohamed Iqbal Khan | C12: =IF('02_Common_Member_Master'!J12="","",'02_Common_Member_Master'!J12) | D12: =IF('02_Common_Member_Master'!K12="","",'02_Common_Member_Master'!K12) | E12: =IF('02_Common_Member_Master'!L12="","",'02_Common_Member_Master'!L12) | F12: =IF('02_Common_Member_Master'!M12="","",'02_Common_Member_Master'!M12) | G12: =IF('02_Common_Member_Master'!N12="","",'02_Common_Member_Master'!N12) | I12: =IF('02_Common_Member_Master'!#REF!="","",'02_Common_Member_Master'!#REF!) -> #REF!
A13: =IF('02_Common_Member_Master'!A13="","",'02_Common_Member_Master'!A13) -> 11 | B13: =IF('02_Common_Member_Master'!I13="","",'02_Common_Member_Master'!I13) -> Mohd Hashim Anwarul Haque Khan | C13: =IF('02_Common_Member_Master'!J13="","",'02_Common_Member_Master'!J13) | D13: =IF('02_Common_Member_Master'!K13="","",'02_Common_Member_Master'!K13) | E13: =IF('02_Common_Member_Master'!L13="","",'02_Common_Member_Master'!L13) | F13: =IF('02_Common_Member_Master'!M13="","",'02_Common_Member_Master'!M13) | G13: =IF('02_Common_Member_Master'!N13="","",'02_Common_Member_Master'!N13) | I13: =IF('02_Common_Member_Master'!#REF!="","",'02_Common_Member_Master'!#REF!) -> #REF!
A14: =IF('02_Common_Member_Master'!A14="","",'02_Common_Member_Master'!A14) -> 12 | B14: =IF('02_Common_Member_Master'!I14="","",'02_Common_Member_Master'!I14) -> Mohammed Shoyab Mohammed Faique Farooque | C14: =IF('02_Common_Member_Master'!J14="","",'02_Common_Member_Master'!J14) | D14: =IF('02_Common_Member_Master'!K14="","",'02_Common_Member_Master'!K14) | E14: =IF('02_Common_Member_Master'!L14="","",'02_Common_Member_Master'!L14) | F14: =IF('02_Common_Member_Master'!M14="","",'02_Common_Member_Master'!M14) | G14: =IF('02_Common_Member_Master'!N14="","",'02_Common_Member_Master'!N14) | I14: =IF('02_Common_Member_Master'!#REF!="","",'02_Common_Member_Master'!#REF!) -> #REF!
... A23: =IF('02_Common_Member_Master'!A23="","",'02_Common_Member_Master'!A23) -> 21 | B23: =IF('02_Common_Member_Master'!I23="","",'02_Common_Member_Master'!I23) -> Sarfaraz Israr Khan | C23: =IF('02_Common_Member_Master'!J23="","",'02_Common_Member_Master'!J23) | D23: =IF('02_Common_Member_Master'!K23="","",'02_Common_Member_Master'!K23) | E23: =IF('02_Common_Member_Master'!L23="","",'02_Common_Member_Master'!L23) | F23: =IF('02_Common_Member_Master'!M23="","",'02_Common_Member_Master'!M23) | G23: =IF('02_Common_Member_Master'!N23="","",'02_Common_Member_Master'!N23) | I23: =IF('02_Common_Member_Master'!#REF!="","",'02_Common_Member_Master'!#REF!) -> #REF!

Sheet 08_Lien_Mark_Register
A1: Sr. No. | B1: Wing / Flat No. | D1: Members Name | J1: Flat Area | K1: Type of Membership | L1: Remarks | M1: PARTICULARS OF LOAN - 1st LOAN | V1: PARTICULARS OF LOAN - 2nd LOAN OR LOAN TOP-UP | AE1: PARTICULARS OF LOAN - 3rd LOAN OR LOAN TOP-UP | AN1: PARTICULARS OF LOAN - 4th LOAN OR LOAN TOP-UP
B2: Wing No. | C2: Flat No. | D2: 1 | E2: 2 | F2: 3 | G2: 4 | H2: 5 | I2: 6 | M2: Name of the Bank | N2: Bank Address | O2: Loan Amount | P2: Period of Loan | Q2: Managing Committee Meeting Date | R2: Resolution No. | S2: Date of NOC given by Society | T2: Date of Documents of Lien Cancellation | U2: Remarks | V2: Name of the Bank | W2: Bank Address | X2: Loan Amount | Y2: Period of Loan | Z2: Managing Committee Meeting Date | AA2: Resolution No. | AB2: Date of NOC given by Society | AC2: Date of Documents of Lien Cancellation | AD2: Remarks | AE2: Name of the Bank | AF2: Bank Address | AG2: Loan Amount | AH2: Period of Loan | AI2: Managing Committee Meeting Date | AJ2: Resolution No. | AK2: Date of NOC given by Society | AL2: Date of Documents of Lien Cancellation | AM2: Remarks | AN2: Name of the Bank | AO2: Bank Address | AP2: Loan Amount | AQ2: Period of Loan | AR2: Managing Committee Meeting Date | AS2: Resolution No. | AT2: Date of NOC given by Society | AU2: Date of Documents of Lien Cancellation | AV2: Remarks
A3: =IF('02_Common_Member_Master'!A3="","",'02_Common_Member_Master'!A3) -> 1 | B3: =IF('02_Common_Member_Master'!#REF!="","",'02_Common_Member_Master'!#REF!) -> #REF! | C3: =IF('02_Common_Member_Master'!#REF!="","",'02_Common_Member_Master'!#REF!) -> #REF! | D3: =IF('02_Common_Member_Master'!I3="","",'02_Common_Member_Master'!I3) -> Nafisha Khatoon Sharif Ahmed Khan | E3: =IF('02_Common_Member_Master'!J3="","",'02_Common_Member_Master'!J3) | F3: =IF('02_Common_Member_Master'!K3="","",'02_Common_Member_Master'!K3) | G3: =IF('02_Common_Member_Master'!L3="","",'02_Common_Member_Master'!L3) | H3: =IF('02_Common_Member_Master'!M3="","",'02_Common_Member_Master'!M3) | I3: =IF('02_Common_Member_Master'!N3="","",'02_Common_Member_Master'!N3)
A4: =IF('02_Common_Member_Master'!A4="","",'02_Common_Member_Master'!A4) -> 2 | B4: =IF('02_Common_Member_Master'!#REF!="","",'02_Common_Member_Master'!#REF!) -> #REF! | C4: =IF('02_Common_Member_Master'!#REF!="","",'02_Common_Member_Master'!#REF!) -> #REF! | D4: =IF('02_Common_Member_Master'!I4="","",'02_Common_Member_Master'!I4) -> Azhar Husain Mazhar Husain Khan | E4: =IF('02_Common_Member_Master'!J4="","",'02_Common_Member_Master'!J4) | F4: =IF('02_Common_Member_Master'!K4="","",'02_Common_Member_Master'!K4) | G4: =IF('02_Common_Member_Master'!L4="","",'02_Common_Member_Master'!L4) | H4: =IF('02_Common_Member_Master'!M4="","",'02_Common_Member_Master'!M4) | I4: =IF('02_Common_Member_Master'!N4="","",'02_Common_Member_Master'!N4)
A5: =IF('02_Common_Member_Master'!A5="","",'02_Common_Member_Master'!A5) -> 3 | B5: =IF('02_Common_Member_Master'!#REF!="","",'02_Common_Member_Master'!#REF!) -> #REF! | C5: =IF('02_Common_Member_Master'!#REF!="","",'02_Common_Member_Master'!#REF!) -> #REF! | D5: =IF('02_Common_Member_Master'!I5="","",'02_Common_Member_Master'!I5) -> Abdul Malik Azhar Husain Khan | E5: =IF('02_Common_Member_Master'!J5="","",'02_Common_Member_Master'!J5) | F5: =IF('02_Common_Member_Master'!K5="","",'02_Common_Member_Master'!K5) | G5: =IF('02_Common_Member_Master'!L5="","",'02_Common_Member_Master'!L5) | H5: =IF('02_Common_Member_Master'!M5="","",'02_Common_Member_Master'!M5) | I5: =IF('02_Common_Member_Master'!N5="","",'02_Common_Member_Master'!N5)
A6: =IF('02_Common_Member_Master'!A6="","",'02_Common_Member_Master'!A6) -> 4 | B6: =IF('02_Common_Member_Master'!#REF!="","",'02_Common_Member_Master'!#REF!) -> #REF! | C6: =IF('02_Common_Member_Master'!#REF!="","",'02_Common_Member_Master'!#REF!) -> #REF! | D6: =IF('02_Common_Member_Master'!I6="","",'02_Common_Member_Master'!I6) -> Abdul Wadood Abdul Mannan Sayyed | E6: =IF('02_Common_Member_Master'!J6="","",'02_Common_Member_Master'!J6) | F6: =IF('02_Common_Member_Master'!K6="","",'02_Common_Member_Master'!K6) | G6: =IF('02_Common_Member_Master'!L6="","",'02_Common_Member_Master'!L6) | H6: =IF('02_Common_Member_Master'!M6="","",'02_Common_Member_Master'!M6) | I6: =IF('02_Common_Member_Master'!N6="","",'02_Common_Member_Master'!N6)
A7: =IF('02_Common_Member_Master'!A7="","",'02_Common_Member_Master'!A7) -> 5 | B7: =IF('02_Common_Member_Master'!#REF!="","",'02_Common_Member_Master'!#REF!) -> #REF! | C7: =IF('02_Common_Member_Master'!#REF!="","",'02_Common_Member_Master'!#REF!) -> #REF! | D7: =IF('02_Common_Member_Master'!I7="","",'02_Common_Member_Master'!I7) -> Abdulhai Abdul Mannan Sayyed | E7: =IF('02_Common_Member_Master'!J7="","",'02_Common_Member_Master'!J7) | F7: =IF('02_Common_Member_Master'!K7="","",'02_Common_Member_Master'!K7) | G7: =IF('02_Common_Member_Master'!L7="","",'02_Common_Member_Master'!L7) | H7: =IF('02_Common_Member_Master'!M7="","",'02_Common_Member_Master'!M7) | I7: =IF('02_Common_Member_Master'!N7="","",'02_Common_Member_Master'!N7)
A8: =IF('02_Common_Member_Master'!A8="","",'02_Common_Member_Master'!A8) -> 6 | B8: =IF('02_Common_Member_Master'!#REF!="","",'02_Common_Member_Master'!#REF!) -> #REF! | C8: =IF('02_Common_Member_Master'!#REF!="","",'02_Common_Member_Master'!#REF!) -> #REF! | D8: =IF('02_Common_Member_Master'!I8="","",'02_Common_Member_Master'!I8) -> Shakeel Ahmed Nazir Ahmed Khan | E8: =IF('02_Common_Member_Master'!J8="","",'02_Common_Member_Master'!J8) | F8: =IF('02_Common_Member_Master'!K8="","",'02_Common_Member_Master'!K8) | G8: =IF('02_Common_Member_Master'!L8="","",'02_Common_Member_Master'!L8) | H8: =IF('02_Common_Member_Master'!M8="","",'02_Common_Member_Master'!M8) | I8: =IF('02_Common_Member_Master'!N8="","",'02_Common_Member_Master'!N8)
A9: =IF('02_Common_Member_Master'!A9="","",'02_Common_Member_Master'!A9) -> 7 | B9: =IF('02_Common_Member_Master'!#REF!="","",'02_Common_Member_Master'!#REF!) -> #REF! | C9: =IF('02_Common_Member_Master'!#REF!="","",'02_Common_Member_Master'!#REF!) -> #REF! | D9: =IF('02_Common_Member_Master'!I9="","",'02_Common_Member_Master'!I9) -> Mohammed Nawaz Ramzan Ali Shaikh | E9: =IF('02_Common_Member_Master'!J9="","",'02_Common_Member_Master'!J9) | F9: =IF('02_Common_Member_Master'!K9="","",'02_Common_Member_Master'!K9) | G9: =IF('02_Common_Member_Master'!L9="","",'02_Common_Member_Master'!L9) | H9: =IF('02_Common_Member_Master'!M9="","",'02_Common_Member_Master'!M9) | I9: =IF('02_Common_Member_Master'!N9="","",'02_Common_Member_Master'!N9)
A10: =IF('02_Common_Member_Master'!A10="","",'02_Common_Member_Master'!A10) -> 8 | B10: =IF('02_Common_Member_Master'!#REF!="","",'02_Common_Member_Master'!#REF!) -> #REF! | C10: =IF('02_Common_Member_Master'!#REF!="","",'02_Common_Member_Master'!#REF!) -> #REF! | D10: =IF('02_Common_Member_Master'!I10="","",'02_Common_Member_Master'!I10) -> Gulam Husain Kutbullah Khan | E10: =IF('02_Common_Member_Master'!J10="","",'02_Common_Member_Master'!J10) | F10: =IF('02_Common_Member_Master'!K10="","",'02_Common_Member_Master'!K10) | G10: =IF('02_Common_Member_Master'!L10="","",'02_Common_Member_Master'!L10) | H10: =IF('02_Common_Member_Master'!M10="","",'02_Common_Member_Master'!M10) | I10: =IF('02_Common_Member_Master'!N10="","",'02_Common_Member_Master'!N10)
A11: =IF('02_Common_Member_Master'!A11="","",'02_Common_Member_Master'!A11) -> 9 | B11: =IF('02_Common_Member_Master'!#REF!="","",'02_Common_Member_Master'!#REF!) -> #REF! | C11: =IF('02_Common_Member_Master'!#REF!="","",'02_Common_Member_Master'!#REF!) -> #REF! | D11: =IF('02_Common_Member_Master'!I11="","",'02_Common_Member_Master'!I11) -> Sajid Azhar Husain Khan | E11: =IF('02_Common_Member_Master'!J11="","",'02_Common_Member_Master'!J11) | F11: =IF('02_Common_Member_Master'!K11="","",'02_Common_Member_Master'!K11) | G11: =IF('02_Common_Member_Master'!L11="","",'02_Common_Member_Master'!L11) | H11: =IF('02_Common_Member_Master'!M11="","",'02_Common_Member_Master'!M11) | I11: =IF('02_Common_Member_Master'!N11="","",'02_Common_Member_Master'!N11)
A12: =IF('02_Common_Member_Master'!A12="","",'02_Common_Member_Master'!A12) -> 10 | B12: =IF('02_Common_Member_Master'!#REF!="","",'02_Common_Member_Master'!#REF!) -> #REF! | C12: =IF('02_Common_Member_Master'!#REF!="","",'02_Common_Member_Master'!#REF!) -> #REF! | D12: =IF('02_Common_Member_Master'!I12="","",'02_Common_Member_Master'!I12) -> Shakilabanoo Mohamed Iqbal Khan | E12: =IF('02_Common_Member_Master'!J12="","",'02_Common_Member_Master'!J12) | F12: =IF('02_Common_Member_Master'!K12="","",'02_Common_Member_Master'!K12) | G12: =IF('02_Common_Member_Master'!L12="","",'02_Common_Member_Master'!L12) | H12: =IF('02_Common_Member_Master'!M12="","",'02_Common_Member_Master'!M12) | I12: =IF('02_Common_Member_Master'!N12="","",'02_Common_Member_Master'!N12)
A13: =IF('02_Common_Member_Master'!A13="","",'02_Common_Member_Master'!A13) -> 11 | B13: =IF('02_Common_Member_Master'!#REF!="","",'02_Common_Member_Master'!#REF!) -> #REF! | C13: =IF('02_Common_Member_Master'!#REF!="","",'02_Common_Member_Master'!#REF!) -> #REF! | D13: =IF('02_Common_Member_Master'!I13="","",'02_Common_Member_Master'!I13) -> Mohd Hashim Anwarul Haque Khan | E13: =IF('02_Common_Member_Master'!J13="","",'02_Common_Member_Master'!J13) | F13: =IF('02_Common_Member_Master'!K13="","",'02_Common_Member_Master'!K13) | G13: =IF('02_Common_Member_Master'!L13="","",'02_Common_Member_Master'!L13) | H13: =IF('02_Common_Member_Master'!M13="","",'02_Common_Member_Master'!M13) | I13: =IF('02_Common_Member_Master'!N13="","",'02_Common_Member_Master'!N13)
A14: =IF('02_Common_Member_Master'!A14="","",'02_Common_Member_Master'!A14) -> 12 | B14: =IF('02_Common_Member_Master'!#REF!="","",'02_Common_Member_Master'!#REF!) -> #REF! | C14: =IF('02_Common_Member_Master'!#REF!="","",'02_Common_Member_Master'!#REF!) -> #REF! | D14: =IF('02_Common_Member_Master'!I14="","",'02_Common_Member_Master'!I14) -> Mohammed Shoyab Mohammed Faique Farooque | E14: =IF('02_Common_Member_Master'!J14="","",'02_Common_Member_Master'!J14) | F14: =IF('02_Common_Member_Master'!K14="","",'02_Common_Member_Master'!K14) | G14: =IF('02_Common_Member_Master'!L14="","",'02_Common_Member_Master'!L14) | H14: =IF('02_Common_Member_Master'!M14="","",'02_Common_Member_Master'!M14) | I14: =IF('02_Common_Member_Master'!N14="","",'02_Common_Member_Master'!N14)
... A23: =IF('02_Common_Member_Master'!A23="","",'02_Common_Member_Master'!A23) -> 21 | B23: =IF('02_Common_Member_Master'!#REF!="","",'02_Common_Member_Master'!#REF!) -> #REF! | C23: =IF('02_Common_Member_Master'!#REF!="","",'02_Common_Member_Master'!#REF!) -> #REF! | D23: =IF('02_Common_Member_Master'!I23="","",'02_Common_Member_Master'!I23) -> Sarfaraz Israr Khan | E23: =IF('02_Common_Member_Master'!J23="","",'02_Common_Member_Master'!J23) | F23: =IF('02_Common_Member_Master'!K23="","",'02_Common_Member_Master'!K23) | G23: =IF('02_Common_Member_Master'!L23="","",'02_Common_Member_Master'!L23) | H23: =IF('02_Common_Member_Master'!M23="","",'02_Common_Member_Master'!M23) | I23: =IF('02_Common_Member_Master'!N23="","",'02_Common_Member_Master'!N23)

Sheet 09_Share_Certificate
A1: Sr. No. | B1: Share Certificate No. | C1: No. of Shares | D1: Member's Register No. | E1: Flat No. | F1: Authorised Capital Details | I1: Members Name Full (Ownership Details) | L1: Share Distinctive Numbers | N1: Total Value of Shares Rs. | O1: In Lieu of Old Certificate | Q1: MEMORANDUM OF TRANSFERS - 1st TRANSFER | V1: MEMORANDUM OF TRANSFERS - 2nd TRANSFER | AA1: MEMORANDUM OF TRANSFERS - 3rd TRANSFER | AF1: MEMORANDUM OF TRANSFERS - 4th TRANSFER
F2: Authorised Share Capital Rs. | G2: Total Authorised Shares | H2: Value of One Share | I2: 1st Owner | J2: 2nd Owner | K2: 3rd Owner | L2: From | M2: To | O2: Old Share Certificate No. | P2: Date of Issue | Q2: Date of transfer | R2: Transfer No. | S2: Register No. of transfer | T2: To whom Transfered | U2: Register No. of transferee | V2: Date of transfer | W2: Transfer No. | X2: Register No. of transfer | Y2: To whom Transfered | Z2: Register No. of transferee | AA2: Date of transfer | AB2: Transfer No. | AC2: Register No. of transfer | AD2: To whom Transfered | AE2: Register No. of transferee | AF2: Date of transfer | AG2: Transfer No. | AH2: Register No. of transfer | AI2: To whom Transfered | AJ2: Register No. of transferee
A3: =IF('02_Common_Member_Master'!A3="","",'02_Common_Member_Master'!A3) -> 1 | B3: =IF('02_Common_Member_Master'!C3="","",'02_Common_Member_Master'!C3) -> 1 | C3: =IF('02_Common_Member_Master'!D3="","",'02_Common_Member_Master'!D3) -> 10 (Ten) | D3: =IF('02_Common_Member_Master'!B3="","",'02_Common_Member_Master'!B3) -> 1 | E3: =IF('02_Common_Member_Master'!#REF!="","",'02_Common_Member_Master'!#REF!) -> #REF! | H3: =IF('02_Common_Member_Master'!E3="","",'02_Common_Member_Master'!E3) -> 50/- Each | I3: =IF('02_Common_Member_Master'!I3="","",'02_Common_Member_Master'!I3) -> Nafisha Khatoon Sharif Ahmed Khan | J3: =IF('02_Common_Member_Master'!J3="","",'02_Common_Member_Master'!J3) | K3: =IF('02_Common_Member_Master'!K3="","",'02_Common_Member_Master'!K3) | L3: =IF('02_Common_Member_Master'!G3="","",'02_Common_Member_Master'!G3) -> 1 | M3: =IF('02_Common_Member_Master'!H3="","",'02_Common_Member_Master'!H3) -> 10 | N3: =IF('02_Common_Member_Master'!F3="","",'02_Common_Member_Master'!F3) -> 500/-
A4: =IF('02_Common_Member_Master'!A4="","",'02_Common_Member_Master'!A4) -> 2 | B4: =IF('02_Common_Member_Master'!C4="","",'02_Common_Member_Master'!C4) -> 2 | C4: =IF('02_Common_Member_Master'!D4="","",'02_Common_Member_Master'!D4) -> 10 (Ten) | D4: =IF('02_Common_Member_Master'!B4="","",'02_Common_Member_Master'!B4) -> 2 | E4: =IF('02_Common_Member_Master'!#REF!="","",'02_Common_Member_Master'!#REF!) -> #REF! | H4: =IF('02_Common_Member_Master'!E4="","",'02_Common_Member_Master'!E4) -> 50/- Each | I4: =IF('02_Common_Member_Master'!I4="","",'02_Common_Member_Master'!I4) -> Azhar Husain Mazhar Husain Khan | J4: =IF('02_Common_Member_Master'!J4="","",'02_Common_Member_Master'!J4) | K4: =IF('02_Common_Member_Master'!K4="","",'02_Common_Member_Master'!K4) | L4: =IF('02_Common_Member_Master'!G4="","",'02_Common_Member_Master'!G4) -> 11 | M4: =IF('02_Common_Member_Master'!H4="","",'02_Common_Member_Master'!H4) -> 20 | N4: =IF('02_Common_Member_Master'!F4="","",'02_Common_Member_Master'!F4) -> 500/-
A5: =IF('02_Common_Member_Master'!A5="","",'02_Common_Member_Master'!A5) -> 3 | B5: =IF('02_Common_Member_Master'!C5="","",'02_Common_Member_Master'!C5) -> 3 | C5: =IF('02_Common_Member_Master'!D5="","",'02_Common_Member_Master'!D5) -> 10 (Ten) | D5: =IF('02_Common_Member_Master'!B5="","",'02_Common_Member_Master'!B5) -> 3 | E5: =IF('02_Common_Member_Master'!#REF!="","",'02_Common_Member_Master'!#REF!) -> #REF! | H5: =IF('02_Common_Member_Master'!E5="","",'02_Common_Member_Master'!E5) -> 50/- Each | I5: =IF('02_Common_Member_Master'!I5="","",'02_Common_Member_Master'!I5) -> Abdul Malik Azhar Husain Khan | J5: =IF('02_Common_Member_Master'!J5="","",'02_Common_Member_Master'!J5) | K5: =IF('02_Common_Member_Master'!K5="","",'02_Common_Member_Master'!K5) | L5: =IF('02_Common_Member_Master'!G5="","",'02_Common_Member_Master'!G5) -> 21 | M5: =IF('02_Common_Member_Master'!H5="","",'02_Common_Member_Master'!H5) -> 30 | N5: =IF('02_Common_Member_Master'!F5="","",'02_Common_Member_Master'!F5) -> 500/-
A6: =IF('02_Common_Member_Master'!A6="","",'02_Common_Member_Master'!A6) -> 4 | B6: =IF('02_Common_Member_Master'!C6="","",'02_Common_Member_Master'!C6) -> 4 | C6: =IF('02_Common_Member_Master'!D6="","",'02_Common_Member_Master'!D6) -> 10 (Ten) | D6: =IF('02_Common_Member_Master'!B6="","",'02_Common_Member_Master'!B6) -> 4 | E6: =IF('02_Common_Member_Master'!#REF!="","",'02_Common_Member_Master'!#REF!) -> #REF! | H6: =IF('02_Common_Member_Master'!E6="","",'02_Common_Member_Master'!E6) -> 50/- Each | I6: =IF('02_Common_Member_Master'!I6="","",'02_Common_Member_Master'!I6) -> Abdul Wadood Abdul Mannan Sayyed | J6: =IF('02_Common_Member_Master'!J6="","",'02_Common_Member_Master'!J6) | K6: =IF('02_Common_Member_Master'!K6="","",'02_Common_Member_Master'!K6) | L6: =IF('02_Common_Member_Master'!G6="","",'02_Common_Member_Master'!G6) -> 31 | M6: =IF('02_Common_Member_Master'!H6="","",'02_Common_Member_Master'!H6) -> 40 | N6: =IF('02_Common_Member_Master'!F6="","",'02_Common_Member_Master'!F6) -> 500/-
A7: =IF('02_Common_Member_Master'!A7="","",'02_Common_Member_Master'!A7) -> 5 | B7: =IF('02_Common_Member_Master'!C7="","",'02_Common_Member_Master'!C7) -> 5 | C7: =IF('02_Common_Member_Master'!D7="","",'02_Common_Member_Master'!D7) -> 10 (Ten) | D7: =IF('02_Common_Member_Master'!B7="","",'02_Common_Member_Master'!B7) -> 5 | E7: =IF('02_Common_Member_Master'!#REF!="","",'02_Common_Member_Master'!#REF!) -> #REF! | H7: =IF('02_Common_Member_Master'!E7="","",'02_Common_Member_Master'!E7) -> 50/- Each | I7: =IF('02_Common_Member_Master'!I7="","",'02_Common_Member_Master'!I7) -> Abdulhai Abdul Mannan Sayyed | J7: =IF('02_Common_Member_Master'!J7="","",'02_Common_Member_Master'!J7) | K7: =IF('02_Common_Member_Master'!K7="","",'02_Common_Member_Master'!K7) | L7: =IF('02_Common_Member_Master'!G7="","",'02_Common_Member_Master'!G7) -> 41 | M7: =IF('02_Common_Member_Master'!H7="","",'02_Common_Member_Master'!H7) -> 50 | N7: =IF('02_Common_Member_Master'!F7="","",'02_Common_Member_Master'!F7) -> 500/-
A8: =IF('02_Common_Member_Master'!A8="","",'02_Common_Member_Master'!A8) -> 6 | B8: =IF('02_Common_Member_Master'!C8="","",'02_Common_Member_Master'!C8) -> 6 | C8: =IF('02_Common_Member_Master'!D8="","",'02_Common_Member_Master'!D8) -> 10 (Ten) | D8: =IF('02_Common_Member_Master'!B8="","",'02_Common_Member_Master'!B8) -> 6 | E8: =IF('02_Common_Member_Master'!#REF!="","",'02_Common_Member_Master'!#REF!) -> #REF! | H8: =IF('02_Common_Member_Master'!E8="","",'02_Common_Member_Master'!E8) -> 50/- Each | I8: =IF('02_Common_Member_Master'!I8="","",'02_Common_Member_Master'!I8) -> Shakeel Ahmed Nazir Ahmed Khan | J8: =IF('02_Common_Member_Master'!J8="","",'02_Common_Member_Master'!J8) | K8: =IF('02_Common_Member_Master'!K8="","",'02_Common_Member_Master'!K8) | L8: =IF('02_Common_Member_Master'!G8="","",'02_Common_Member_Master'!G8) -> 51 | M8: =IF('02_Common_Member_Master'!H8="","",'02_Common_Member_Master'!H8) -> 60 | N8: =IF('02_Common_Member_Master'!F8="","",'02_Common_Member_Master'!F8) -> 500/-
A9: =IF('02_Common_Member_Master'!A9="","",'02_Common_Member_Master'!A9) -> 7 | B9: =IF('02_Common_Member_Master'!C9="","",'02_Common_Member_Master'!C9) -> 7 | C9: =IF('02_Common_Member_Master'!D9="","",'02_Common_Member_Master'!D9) -> 10 (Ten) | D9: =IF('02_Common_Member_Master'!B9="","",'02_Common_Member_Master'!B9) -> 7 | E9: =IF('02_Common_Member_Master'!#REF!="","",'02_Common_Member_Master'!#REF!) -> #REF! | H9: =IF('02_Common_Member_Master'!E9="","",'02_Common_Member_Master'!E9) -> 50/- Each | I9: =IF('02_Common_Member_Master'!I9="","",'02_Common_Member_Master'!I9) -> Mohammed Nawaz Ramzan Ali Shaikh | J9: =IF('02_Common_Member_Master'!J9="","",'02_Common_Member_Master'!J9) | K9: =IF('02_Common_Member_Master'!K9="","",'02_Common_Member_Master'!K9) | L9: =IF('02_Common_Member_Master'!G9="","",'02_Common_Member_Master'!G9) -> 61 | M9: =IF('02_Common_Member_Master'!H9="","",'02_Common_Member_Master'!H9) -> 70 | N9: =IF('02_Common_Member_Master'!F9="","",'02_Common_Member_Master'!F9) -> 500/-
A10: =IF('02_Common_Member_Master'!A10="","",'02_Common_Member_Master'!A10) -> 8 | B10: =IF('02_Common_Member_Master'!C10="","",'02_Common_Member_Master'!C10) -> 8 | C10: =IF('02_Common_Member_Master'!D10="","",'02_Common_Member_Master'!D10) -> 10 (Ten) | D10: =IF('02_Common_Member_Master'!B10="","",'02_Common_Member_Master'!B10) -> 8 | E10: =IF('02_Common_Member_Master'!#REF!="","",'02_Common_Member_Master'!#REF!) -> #REF! | H10: =IF('02_Common_Member_Master'!E10="","",'02_Common_Member_Master'!E10) -> 50/- Each | I10: =IF('02_Common_Member_Master'!I10="","",'02_Common_Member_Master'!I10) -> Gulam Husain Kutbullah Khan | J10: =IF('02_Common_Member_Master'!J10="","",'02_Common_Member_Master'!J10) | K10: =IF('02_Common_Member_Master'!K10="","",'02_Common_Member_Master'!K10) | L10: =IF('02_Common_Member_Master'!G10="","",'02_Common_Member_Master'!G10) -> 71 | M10: =IF('02_Common_Member_Master'!H10="","",'02_Common_Member_Master'!H10) -> 80 | N10: =IF('02_Common_Member_Master'!F10="","",'02_Common_Member_Master'!F10) -> 500/-
A11: =IF('02_Common_Member_Master'!A11="","",'02_Common_Member_Master'!A11) -> 9 | B11: =IF('02_Common_Member_Master'!C11="","",'02_Common_Member_Master'!C11) -> 9 | C11: =IF('02_Common_Member_Master'!D11="","",'02_Common_Member_Master'!D11) -> 10 (Ten) | D11: =IF('02_Common_Member_Master'!B11="","",'02_Common_Member_Master'!B11) -> 9 | E11: =IF('02_Common_Member_Master'!#REF!="","",'02_Common_Member_Master'!#REF!) -> #REF! | H11: =IF('02_Common_Member_Master'!E11="","",'02_Common_Member_Master'!E11) -> 50/- Each | I11: =IF('02_Common_Member_Master'!I11="","",'02_Common_Member_Master'!I11) -> Sajid Azhar Husain Khan | J11: =IF('02_Common_Member_Master'!J11="","",'02_Common_Member_Master'!J11) | K11: =IF('02_Common_Member_Master'!K11="","",'02_Common_Member_Master'!K11) | L11: =IF('02_Common_Member_Master'!G11="","",'02_Common_Member_Master'!G11) -> 81 | M11: =IF('02_Common_Member_Master'!H11="","",'02_Common_Member_Master'!H11) -> 90 | N11: =IF('02_Common_Member_Master'!F11="","",'02_Common_Member_Master'!F11) -> 500/-
A12: =IF('02_Common_Member_Master'!A12="","",'02_Common_Member_Master'!A12) -> 10 | B12: =IF('02_Common_Member_Master'!C12="","",'02_Common_Member_Master'!C12) -> 10 | C12: =IF('02_Common_Member_Master'!D12="","",'02_Common_Member_Master'!D12) -> 10 (Ten) | D12: =IF('02_Common_Member_Master'!B12="","",'02_Common_Member_Master'!B12) -> 10 | E12: =IF('02_Common_Member_Master'!#REF!="","",'02_Common_Member_Master'!#REF!) -> #REF! | H12: =IF('02_Common_Member_Master'!E12="","",'02_Common_Member_Master'!E12) -> 50/- Each | I12: =IF('02_Common_Member_Master'!I12="","",'02_Common_Member_Master'!I12) -> Shakilabanoo Mohamed Iqbal Khan | J12: =IF('02_Common_Member_Master'!J12="","",'02_Common_Member_Master'!J12) | K12: =IF('02_Common_Member_Master'!K12="","",'02_Common_Member_Master'!K12) | L12: =IF('02_Common_Member_Master'!G12="","",'02_Common_Member_Master'!G12) -> 91 | M12: =IF('02_Common_Member_Master'!H12="","",'02_Common_Member_Master'!H12) -> 100 | N12: =IF('02_Common_Member_Master'!F12="","",'02_Common_Member_Master'!F12) -> 500/-
A13: =IF('02_Common_Member_Master'!A13="","",'02_Common_Member_Master'!A13) -> 11 | B13: =IF('02_Common_Member_Master'!C13="","",'02_Common_Member_Master'!C13) -> 11 | C13: =IF('02_Common_Member_Master'!D13="","",'02_Common_Member_Master'!D13) -> 10 (Ten) | D13: =IF('02_Common_Member_Master'!B13="","",'02_Common_Member_Master'!B13) -> 11 | E13: =IF('02_Common_Member_Master'!#REF!="","",'02_Common_Member_Master'!#REF!) -> #REF! | H13: =IF('02_Common_Member_Master'!E13="","",'02_Common_Member_Master'!E13) -> 50/- Each | I13: =IF('02_Common_Member_Master'!I13="","",'02_Common_Member_Master'!I13) -> Mohd Hashim Anwarul Haque Khan | J13: =IF('02_Common_Member_Master'!J13="","",'02_Common_Member_Master'!J13) | K13: =IF('02_Common_Member_Master'!K13="","",'02_Common_Member_Master'!K13) | L13: =IF('02_Common_Member_Master'!G13="","",'02_Common_Member_Master'!G13) -> 101 | M13: =IF('02_Common_Member_Master'!H13="","",'02_Common_Member_Master'!H13) -> 110 | N13: =IF('02_Common_Member_Master'!F13="","",'02_Common_Member_Master'!F13) -> 500/-
A14: =IF('02_Common_Member_Master'!A14="","",'02_Common_Member_Master'!A14) -> 12 | B14: =IF('02_Common_Member_Master'!C14="","",'02_Common_Member_Master'!C14) -> 12 | C14: =IF('02_Common_Member_Master'!D14="","",'02_Common_Member_Master'!D14) -> 10 (Ten) | D14: =IF('02_Common_Member_Master'!B14="","",'02_Common_Member_Master'!B14) -> 12 | E14: =IF('02_Common_Member_Master'!#REF!="","",'02_Common_Member_Master'!#REF!) -> #REF! | H14: =IF('02_Common_Member_Master'!E14="","",'02_Common_Member_Master'!E14) -> 50/- Each | I14: =IF('02_Common_Member_Master'!I14="","",'02_Common_Member_Master'!I14) -> Mohammed Shoyab Mohammed Faique Farooque | J14: =IF('02_Common_Member_Master'!J14="","",'02_Common_Member_Master'!J14) | K14: =IF('02_Common_Member_Master'!K14="","",'02_Common_Member_Master'!K14) | L14: =IF('02_Common_Member_Master'!G14="","",'02_Common_Member_Master'!G14) -> 111 | M14: =IF('02_Common_Member_Master'!H14="","",'02_Common_Member_Master'!H14) -> 120 | N14: =IF('02_Common_Member_Master'!F14="","",'02_Common_Member_Master'!F14) -> 500/-
... A23: =IF('02_Common_Member_Master'!A23="","",'02_Common_Member_Master'!A23) -> 21 | B23: =IF('02_Common_Member_Master'!C23="","",'02_Common_Member_Master'!C23) -> 21 | C23: =IF('02_Common_Member_Master'!D23="","",'02_Common_Member_Master'!D23) -> 10 (Ten) | D23: =IF('02_Common_Member_Master'!B23="","",'02_Common_Member_Master'!B23) -> 21 | E23: =IF('02_Common_Member_Master'!#REF!="","",'02_Common_Member_Master'!#REF!) -> #REF! | H23: =IF('02_Common_Member_Master'!E23="","",'02_Common_Member_Master'!E23) -> 50/- Each | I23: =IF('02_Common_Member_Master'!I23="","",'02_Common_Member_Master'!I23) -> Sarfaraz Israr Khan | J23: =IF('02_Common_Member_Master'!J23="","",'02_Common_Member_Master'!J23) | K23: =IF('02_Common_Member_Master'!K23="","",'02_Common_Member_Master'!K23) | L23: =IF('02_Common_Member_Master'!G23="","",'02_Common_Member_Master'!G23) -> 201 | M23: =IF('02_Common_Member_Master'!H23="","",'02_Common_Member_Master'!H23) -> 210 | N23: =IF('02_Common_Member_Master'!F23="","",'02_Common_Member_Master'!F23) -> 500/-

Sheet 10_Payment_Voucher
A1: Voucher No | B1: SOC-Number | C1: Society Name | D1: Society Address | E1: To (Payee) | F1: Charge To | G1: Particulars | H1: Bank Name | I1: Cheque No | J1: Voucher Date | K1: Bill Amount | L1: Adv. Less/Paid | M1: Sub Total 1 | N1: TDS % | O1: TDS Amount | P1: Sub Total 2 | Q1: CGST % | R1: CGST Amount | S1: Round Off (+/-) | T1: Other (Fine/Adj) | U1: Net Paid (Voucher)

Sheet Notes & Rules
A1: HENU OS MASTER EXCEL TEMPLATE — OPERATIONAL INSTRUCTIONS & RULES
A3: 1. "Common File" is the MASTER SINGLE SOURCE OF TRUTH for all common member and unit details.
A4: 2. "Society Master" provides the society identity (Name, Registration No., Date, Address) for all PDF headers.
A5: 3. Register-specific information (Nomination, Transfers, Loan Lien details) should be entered in the respective register sheet.
A6: 4. Data rows start on Row 4. Each following row represents the next member or unit record.
A7: 5. Common fields in register sheets contain automatic Excel formulas linked to "Common File". Do not overwrite these formulas.
A8: 6. Blank cells must remain blank. Never insert fake or dummy member data.
A9: 7. THIS "Notes & Rules" SHEET IS FOR DOCUMENTATION ONLY AND IS EXPLICITLY IGNORED BY HENU OS DURING DATA EXTRACTION AND PDF GENERATION.
